{
"meta":{"test_sets":[],"test_metrics":[],"learn_metrics":[{"best_value":"Min","name":"Logloss"}],"launch_mode":"Train","parameters":"","iteration_count":1000,"learn_sets":["learn"],"name":"experiment"},
"iterations":[
{"learn":[0.6701453272],"iteration":0,"passed_time":0.004626714128,"remaining_time":4.622087414},
{"learn":[0.646721133],"iteration":1,"passed_time":0.007952362719,"remaining_time":3.968228997},
{"learn":[0.6284099852],"iteration":2,"passed_time":0.01164297448,"remaining_time":3.869348519},
{"learn":[0.6087835341],"iteration":3,"passed_time":0.0158963022,"remaining_time":3.958179247},
{"learn":[0.5882003505],"iteration":4,"passed_time":0.01910596844,"remaining_time":3.802087719},
{"learn":[0.5712770872],"iteration":5,"passed_time":0.02311874734,"remaining_time":3.830005809},
{"learn":[0.5524176961],"iteration":6,"passed_time":0.0266913542,"remaining_time":3.786359245},
{"learn":[0.5355958576],"iteration":7,"passed_time":0.0301740497,"remaining_time":3.741582162},
{"learn":[0.5200285878],"iteration":8,"passed_time":0.03397318207,"remaining_time":3.740824826},
{"learn":[0.5054439325],"iteration":9,"passed_time":0.03798923675,"remaining_time":3.760934438},
{"learn":[0.489411731],"iteration":10,"passed_time":0.04193918155,"remaining_time":3.770713686},
{"learn":[0.4764657108],"iteration":11,"passed_time":0.04577096588,"remaining_time":3.768476191},
{"learn":[0.4642023658],"iteration":12,"passed_time":0.05007354541,"remaining_time":3.80173764},
{"learn":[0.4510952162],"iteration":13,"passed_time":0.05364461454,"remaining_time":3.778113567},
{"learn":[0.4381538745],"iteration":14,"passed_time":0.05783629533,"remaining_time":3.797916727},
{"learn":[0.4262645094],"iteration":15,"passed_time":0.06182779546,"remaining_time":3.802409421},
{"learn":[0.4159096934],"iteration":16,"passed_time":0.065162118,"remaining_time":3.767903647},
{"learn":[0.4052808201],"iteration":17,"passed_time":0.06898571916,"remaining_time":3.763554234},
{"learn":[0.3976356302],"iteration":18,"passed_time":0.07266362157,"remaining_time":3.751737513},
{"learn":[0.3890578301],"iteration":19,"passed_time":0.07628920171,"remaining_time":3.738170884},
{"learn":[0.3811747233],"iteration":20,"passed_time":0.08060921364,"remaining_time":3.757924769},
{"learn":[0.3714287137],"iteration":21,"passed_time":0.0838784789,"remaining_time":3.728779653},
{"learn":[0.361219103],"iteration":22,"passed_time":0.08720697196,"remaining_time":3.704400505},
{"learn":[0.3531757038],"iteration":23,"passed_time":0.090788557,"remaining_time":3.692067985},
{"learn":[0.3455288186],"iteration":24,"passed_time":0.0943379774,"remaining_time":3.679181119},
{"learn":[0.3392319391],"iteration":25,"passed_time":0.09770090523,"remaining_time":3.660026219},
{"learn":[0.3330611217],"iteration":26,"passed_time":0.1011498977,"remaining_time":3.645142611},
{"learn":[0.3254106524],"iteration":27,"passed_time":0.1044596066,"remaining_time":3.626240629},
{"learn":[0.3215928433],"iteration":28,"passed_time":0.1081941728,"remaining_time":3.622639371},
{"learn":[0.3160724023],"iteration":29,"passed_time":0.1122224657,"remaining_time":3.628526392},
{"learn":[0.3109823621],"iteration":30,"passed_time":0.1161383379,"remaining_time":3.630259659},
{"learn":[0.3073824897],"iteration":31,"passed_time":0.1195371162,"remaining_time":3.615997764},
{"learn":[0.3017822137],"iteration":32,"passed_time":0.123671967,"remaining_time":3.623963396},
{"learn":[0.2985168114],"iteration":33,"passed_time":0.1315439136,"remaining_time":3.737394721},
{"learn":[0.2929448853],"iteration":34,"passed_time":0.1360817977,"remaining_time":3.751969566},
{"learn":[0.2883156134],"iteration":35,"passed_time":0.1395325784,"remaining_time":3.736372376},
{"learn":[0.2828239945],"iteration":36,"passed_time":0.1432587517,"remaining_time":3.728599402},
{"learn":[0.2773342642],"iteration":37,"passed_time":0.1472136001,"remaining_time":3.726828508},
{"learn":[0.2734881051],"iteration":38,"passed_time":0.1505333594,"remaining_time":3.70929637},
{"learn":[0.2693075403],"iteration":39,"passed_time":0.1539995891,"remaining_time":3.695990137},
{"learn":[0.2656018436],"iteration":40,"passed_time":0.158081066,"remaining_time":3.697554689},
{"learn":[0.2625151472],"iteration":41,"passed_time":0.162075912,"remaining_time":3.696874373},
{"learn":[0.2585911275],"iteration":42,"passed_time":0.1662131115,"remaining_time":3.699208086},
{"learn":[0.2553244375],"iteration":43,"passed_time":0.1694059713,"remaining_time":3.68072974},
{"learn":[0.2510494871],"iteration":44,"passed_time":0.1728458946,"remaining_time":3.668173985},
{"learn":[0.248357695],"iteration":45,"passed_time":0.1774629135,"remaining_time":3.680426509},
{"learn":[0.2453019669],"iteration":46,"passed_time":0.181690444,"remaining_time":3.684063685},
{"learn":[0.2407364342],"iteration":47,"passed_time":0.1851022888,"remaining_time":3.671195394},
{"learn":[0.2375346209],"iteration":48,"passed_time":0.1890794617,"remaining_time":3.669685063},
{"learn":[0.2334914067],"iteration":49,"passed_time":0.1925649109,"remaining_time":3.658733307},
{"learn":[0.2305787807],"iteration":50,"passed_time":0.1954652812,"remaining_time":3.637187291},
{"learn":[0.2281805755],"iteration":51,"passed_time":0.1985660819,"remaining_time":3.620012416},
{"learn":[0.2263669257],"iteration":52,"passed_time":0.2015085127,"remaining_time":3.600538896},
{"learn":[0.2241202138],"iteration":53,"passed_time":0.204446031,"remaining_time":3.581591581},
{"learn":[0.2216702661],"iteration":54,"passed_time":0.2077787107,"remaining_time":3.570016029},
{"learn":[0.2191865602],"iteration":55,"passed_time":0.2119543053,"remaining_time":3.572944003},
{"learn":[0.2179121186],"iteration":56,"passed_time":0.2160554133,"remaining_time":3.574390435},
{"learn":[0.2150841779],"iteration":57,"passed_time":0.2192420133,"remaining_time":3.560792699},
{"learn":[0.2134929931],"iteration":58,"passed_time":0.2229059341,"remaining_time":3.555160745},
{"learn":[0.2111394697],"iteration":59,"passed_time":0.2259066919,"remaining_time":3.539204839},
{"learn":[0.2086438314],"iteration":60,"passed_time":0.2290305626,"remaining_time":3.525568824},
{"learn":[0.2061082113],"iteration":61,"passed_time":0.2318541018,"remaining_time":3.507728185},
{"learn":[0.2041415229],"iteration":62,"passed_time":0.2345970042,"remaining_time":3.489164967},
{"learn":[0.2021648337],"iteration":63,"passed_time":0.2374505305,"remaining_time":3.472714008},
{"learn":[0.2002096485],"iteration":64,"passed_time":0.2403348258,"remaining_time":3.457124033},
{"learn":[0.1987329797],"iteration":65,"passed_time":0.2430773025,"remaining_time":3.43991213},
{"learn":[0.1964089223],"iteration":66,"passed_time":0.2459112327,"remaining_time":3.424405673},
{"learn":[0.19531059],"iteration":67,"passed_time":0.2485136643,"remaining_time":3.406099045},
{"learn":[0.1931738444],"iteration":68,"passed_time":0.2514262732,"remaining_time":3.392432758},
{"learn":[0.1912007821],"iteration":69,"passed_time":0.255266421,"remaining_time":3.391396736},
{"learn":[0.1898758214],"iteration":70,"passed_time":0.2586779045,"remaining_time":3.384672863},
{"learn":[0.1875018027],"iteration":71,"passed_time":0.2618321289,"remaining_time":3.374725217},
{"learn":[0.1861386842],"iteration":72,"passed_time":0.2649047096,"remaining_time":3.363926929},
{"learn":[0.1848020487],"iteration":73,"passed_time":0.2687606767,"remaining_time":3.363140359},
{"learn":[0.1824482892],"iteration":74,"passed_time":0.271664452,"remaining_time":3.350528241},
{"learn":[0.180723252],"iteration":75,"passed_time":0.2744755312,"remaining_time":3.337044617},
{"learn":[0.1785510314],"iteration":76,"passed_time":0.2771434457,"remaining_time":3.322122083},
{"learn":[0.1770986243],"iteration":77,"passed_time":0.279916135,"remaining_time":3.308752262},
{"learn":[0.1755277953],"iteration":78,"passed_time":0.2825720005,"remaining_time":3.294288766},
{"learn":[0.1746530761],"iteration":79,"passed_time":0.2853596733,"remaining_time":3.281636243},
{"learn":[0.173083685],"iteration":80,"passed_time":0.2882383188,"remaining_time":3.270259444},
{"learn":[0.1720747485],"iteration":81,"passed_time":0.2911075605,"remaining_time":3.25898464},
{"learn":[0.1710888826],"iteration":82,"passed_time":0.294056827,"remaining_time":3.24879651},
{"learn":[0.1702390046],"iteration":83,"passed_time":0.2966638958,"remaining_time":3.23504915},
{"learn":[0.168870435],"iteration":84,"passed_time":0.2999689023,"remaining_time":3.229077007},
{"learn":[0.1673990456],"iteration":85,"passed_time":0.3042133751,"remaining_time":3.233151452},
{"learn":[0.1657679433],"iteration":86,"passed_time":0.3077561751,"remaining_time":3.229671125},
{"learn":[0.1648562038],"iteration":87,"passed_time":0.3108157661,"remaining_time":3.221181575},
{"learn":[0.1634496804],"iteration":88,"passed_time":0.3137789942,"remaining_time":3.211827682},
{"learn":[0.1624999979],"iteration":89,"passed_time":0.316768945,"remaining_time":3.202886},
{"learn":[0.1612695192],"iteration":90,"passed_time":0.3196299832,"remaining_time":3.192787414},
{"learn":[0.1601643623],"iteration":91,"passed_time":0.3226281369,"remaining_time":3.184199438},
{"learn":[0.159414793],"iteration":92,"passed_time":0.3257617335,"remaining_time":3.177052605},
{"learn":[0.1587900733],"iteration":93,"passed_time":0.3287933401,"remaining_time":3.16900815},
{"learn":[0.1580646585],"iteration":94,"passed_time":0.3316583038,"remaining_time":3.159481736},
{"learn":[0.1566789093],"iteration":95,"passed_time":0.3345374811,"remaining_time":3.150227947},
{"learn":[0.1553496349],"iteration":96,"passed_time":0.3371891701,"remaining_time":3.138987841},
{"learn":[0.1540763522],"iteration":97,"passed_time":0.3399805887,"remaining_time":3.129209092},
{"learn":[0.1530831574],"iteration":98,"passed_time":0.3425374386,"remaining_time":3.117436689},
{"learn":[0.1521333139],"iteration":99,"passed_time":0.345392307,"remaining_time":3.108530763},
{"learn":[0.1508452768],"iteration":100,"passed_time":0.348404398,"remaining_time":3.101144097},
{"learn":[0.1502694346],"iteration":101,"passed_time":0.351459325,"remaining_time":3.094220332},
{"learn":[0.1493255894],"iteration":102,"passed_time":0.3545075775,"remaining_time":3.087313563},
{"learn":[0.1485782414],"iteration":103,"passed_time":0.3573332306,"remaining_time":3.078563217},
{"learn":[0.1475583384],"iteration":104,"passed_time":0.3602479184,"remaining_time":3.070684638},
{"learn":[0.1461747782],"iteration":105,"passed_time":0.3632942325,"remaining_time":3.064009848},
{"learn":[0.1454965133],"iteration":106,"passed_time":0.3659070704,"remaining_time":3.053785176},
{"learn":[0.1446132204],"iteration":107,"passed_time":0.3685584789,"remaining_time":3.04402003},
{"learn":[0.1434321772],"iteration":108,"passed_time":0.371188614,"remaining_time":3.034211515},
{"learn":[0.142658518],"iteration":109,"passed_time":0.3740111116,"remaining_time":3.026089903},
{"learn":[0.1421066477],"iteration":110,"passed_time":0.3766720351,"remaining_time":3.016769722},
{"learn":[0.1411820209],"iteration":111,"passed_time":0.3794790436,"remaining_time":3.008726703},
{"learn":[0.1403083426],"iteration":112,"passed_time":0.3821563629,"remaining_time":2.999758353},
{"learn":[0.1398330023],"iteration":113,"passed_time":0.3849538958,"remaining_time":2.991834664},
{"learn":[0.1392415794],"iteration":114,"passed_time":0.3876110234,"remaining_time":2.982919615},
{"learn":[0.1386564874],"iteration":115,"passed_time":0.390402217,"remaining_time":2.975134137},
{"learn":[0.1372986269],"iteration":116,"passed_time":0.3933140797,"remaining_time":2.968344721},
{"learn":[0.1367955375],"iteration":117,"passed_time":0.3961205674,"remaining_time":2.960833394},
{"learn":[0.1359879055],"iteration":118,"passed_time":0.3996020557,"remaining_time":2.958398412},
{"learn":[0.1356643162],"iteration":119,"passed_time":0.4025597355,"remaining_time":2.952104727},
{"learn":[0.1350825936],"iteration":120,"passed_time":0.4060096197,"remaining_time":2.949441783},
{"learn":[0.1346418485],"iteration":121,"passed_time":0.4099088,"remaining_time":2.949999397},
{"learn":[0.1339669959],"iteration":122,"passed_time":0.4135767665,"remaining_time":2.948835969},
{"learn":[0.1331638814],"iteration":123,"passed_time":0.4163755971,"remaining_time":2.941492121},
{"learn":[0.132340851],"iteration":124,"passed_time":0.4194755055,"remaining_time":2.936328538},
{"learn":[0.1316960331],"iteration":125,"passed_time":0.4223987317,"remaining_time":2.929972155},
{"learn":[0.1308955476],"iteration":126,"passed_time":0.425186319,"remaining_time":2.922737453},
{"learn":[0.1304074058],"iteration":127,"passed_time":0.4277777833,"remaining_time":2.914236149},
{"learn":[0.1297566861],"iteration":128,"passed_time":0.4304468296,"remaining_time":2.906350299},
{"learn":[0.1290717145],"iteration":129,"passed_time":0.4333981347,"remaining_time":2.90043367},
{"learn":[0.128081814],"iteration":130,"passed_time":0.4360139673,"remaining_time":2.892336928},
{"learn":[0.1272600928],"iteration":131,"passed_time":0.4387419162,"remaining_time":2.885060479},
{"learn":[0.1267369266],"iteration":132,"passed_time":0.4414001852,"remaining_time":2.8773982},
{"learn":[0.1263277185],"iteration":133,"passed_time":0.4442749849,"remaining_time":2.871209977},
{"learn":[0.1256734684],"iteration":134,"passed_time":0.4471941742,"remaining_time":2.865355264},
{"learn":[0.1254260121],"iteration":135,"passed_time":0.4510956384,"remaining_time":2.865784056},
{"learn":[0.1252152755],"iteration":136,"passed_time":0.4540288055,"remaining_time":2.860050067},
{"learn":[0.1246594672],"iteration":137,"passed_time":0.456873052,"remaining_time":2.853801238},
{"learn":[0.1238568785],"iteration":138,"passed_time":0.4594984696,"remaining_time":2.846245916},
{"learn":[0.1234463934],"iteration":139,"passed_time":0.4622186964,"remaining_time":2.839343421},
{"learn":[0.1228381343],"iteration":140,"passed_time":0.4649284561,"remaining_time":2.832436481},
{"learn":[0.1223785787],"iteration":141,"passed_time":0.4677836256,"remaining_time":2.826467259},
{"learn":[0.1218122759],"iteration":142,"passed_time":0.4704391907,"remaining_time":2.819345359},
{"learn":[0.1213930669],"iteration":143,"passed_time":0.4731039101,"remaining_time":2.81233991},
{"learn":[0.1208011933],"iteration":144,"passed_time":0.4757089859,"remaining_time":2.805042641},
{"learn":[0.1204919614],"iteration":145,"passed_time":0.4783673654,"remaining_time":2.798121438},
{"learn":[0.1198339663],"iteration":146,"passed_time":0.4811258222,"remaining_time":2.791838955},
{"learn":[0.1194734962],"iteration":147,"passed_time":0.4838603818,"remaining_time":2.785466522},
{"learn":[0.1186294341],"iteration":148,"passed_time":0.4867779889,"remaining_time":2.780188379},
{"learn":[0.1183630706],"iteration":149,"passed_time":0.490083415,"remaining_time":2.777139352},
{"learn":[0.1177094107],"iteration":150,"passed_time":0.4935255662,"remaining_time":2.774855667},
{"learn":[0.1169918291],"iteration":151,"passed_time":0.4969688857,"remaining_time":2.772563257},
{"learn":[0.1165681348],"iteration":152,"passed_time":0.4997402375,"remaining_time":2.766535825},
{"learn":[0.1160409662],"iteration":153,"passed_time":0.5025915256,"remaining_time":2.76098981},
{"learn":[0.11564295],"iteration":154,"passed_time":0.505775416,"remaining_time":2.757291784},
{"learn":[0.1152609008],"iteration":155,"passed_time":0.5087944119,"remaining_time":2.752708228},
{"learn":[0.1147189563],"iteration":156,"passed_time":0.5115315358,"remaining_time":2.746631113},
{"learn":[0.1143159719],"iteration":157,"passed_time":0.5143692125,"remaining_time":2.741132133},
{"learn":[0.1138851311],"iteration":158,"passed_time":0.517025629,"remaining_time":2.734707886},
{"learn":[0.1133819881],"iteration":159,"passed_time":0.5197200351,"remaining_time":2.728530184},
{"learn":[0.1131388454],"iteration":160,"passed_time":0.5223685441,"remaining_time":2.722156574},
{"learn":[0.1128307938],"iteration":161,"passed_time":0.5251067986,"remaining_time":2.716293193},
{"learn":[0.1121636027],"iteration":162,"passed_time":0.5279196209,"remaining_time":2.710851059},
{"learn":[0.1118193893],"iteration":163,"passed_time":0.5305992037,"remaining_time":2.704761795},
{"learn":[0.1114995127],"iteration":164,"passed_time":0.5335913686,"remaining_time":2.700295714},
{"learn":[0.1111908603],"iteration":165,"passed_time":0.536572976,"remaining_time":2.695794349},
{"learn":[0.1109687065],"iteration":166,"passed_time":0.539623487,"remaining_time":2.691654878},
{"learn":[0.1104720232],"iteration":167,"passed_time":0.5425328865,"remaining_time":2.686829533},
{"learn":[0.1101244941],"iteration":168,"passed_time":0.5454844369,"remaining_time":2.682234125},
{"learn":[0.1097756988],"iteration":169,"passed_time":0.5482673817,"remaining_time":2.676834863},
{"learn":[0.1094679692],"iteration":170,"passed_time":0.5508947427,"remaining_time":2.67071194},
{"learn":[0.1091794471],"iteration":171,"passed_time":0.5537383434,"remaining_time":2.66567063},
{"learn":[0.1089282458],"iteration":172,"passed_time":0.5564639486,"remaining_time":2.660090668},
{"learn":[0.1086843413],"iteration":173,"passed_time":0.559224398,"remaining_time":2.654708924},
{"learn":[0.1085264096],"iteration":174,"passed_time":0.5618912214,"remaining_time":2.648915758},
{"learn":[0.1081537925],"iteration":175,"passed_time":0.564511461,"remaining_time":2.642940022},
{"learn":[0.1075877687],"iteration":176,"passed_time":0.5672266804,"remaining_time":2.637443831},
{"learn":[0.1073301935],"iteration":177,"passed_time":0.5699378724,"remaining_time":2.631960287},
{"learn":[0.1071120636],"iteration":178,"passed_time":0.5727578059,"remaining_time":2.627006473},
{"learn":[0.1066248769],"iteration":179,"passed_time":0.5754989658,"remaining_time":2.621717511},
{"learn":[0.106325281],"iteration":180,"passed_time":0.5784682498,"remaining_time":2.617488931},
{"learn":[0.1057435477],"iteration":181,"passed_time":0.58107622,"remaining_time":2.611650264},
{"learn":[0.1049332008],"iteration":182,"passed_time":0.583857437,"remaining_time":2.606620361},
{"learn":[0.1046064889],"iteration":183,"passed_time":0.5866144272,"remaining_time":2.60150746},
{"learn":[0.1043232892],"iteration":184,"passed_time":0.589490263,"remaining_time":2.596943591},
{"learn":[0.1040271056],"iteration":185,"passed_time":0.5922754425,"remaining_time":2.59200113},
{"learn":[0.1034978553],"iteration":186,"passed_time":0.59506018,"remaining_time":2.58707982},
{"learn":[0.1031530088],"iteration":187,"passed_time":0.5978597575,"remaining_time":2.582245335},
{"learn":[0.1027726336],"iteration":188,"passed_time":0.6010441887,"remaining_time":2.579083794},
{"learn":[0.1024781132],"iteration":189,"passed_time":0.6040190752,"remaining_time":2.575028689},
{"learn":[0.1020599451],"iteration":190,"passed_time":0.6073776415,"remaining_time":2.57261001},
{"learn":[0.1016281922],"iteration":191,"passed_time":0.6103422725,"remaining_time":2.56852373},
{"learn":[0.1014541004],"iteration":192,"passed_time":0.6133875744,"remaining_time":2.564786386},
{"learn":[0.101268999],"iteration":193,"passed_time":0.6160238091,"remaining_time":2.55935665},
{"learn":[0.1009730944],"iteration":194,"passed_time":0.6188793686,"remaining_time":2.554860983},
{"learn":[0.100604952],"iteration":195,"passed_time":0.6215815276,"remaining_time":2.549752797},
{"learn":[0.1003377622],"iteration":196,"passed_time":0.6244015014,"remaining_time":2.545149267},
{"learn":[0.1000882349],"iteration":197,"passed_time":0.6270854505,"remaining_time":2.540012784},
{"learn":[0.09973226083],"iteration":198,"passed_time":0.6300800042,"remaining_time":2.536151173},
{"learn":[0.09919886851],"iteration":199,"passed_time":0.6330604644,"remaining_time":2.532241858},
{"learn":[0.09899239198],"iteration":200,"passed_time":0.6359706999,"remaining_time":2.528062633},
{"learn":[0.09861222065],"iteration":201,"passed_time":0.6391296921,"remaining_time":2.524878685},
{"learn":[0.0982958744],"iteration":202,"passed_time":0.6419315018,"remaining_time":2.520292645},
{"learn":[0.09771565412],"iteration":203,"passed_time":0.6448287121,"remaining_time":2.516096347},
{"learn":[0.09743288365],"iteration":204,"passed_time":0.6480039289,"remaining_time":2.512990846},
{"learn":[0.09706934461],"iteration":205,"passed_time":0.6512011108,"remaining_time":2.50996933},
{"learn":[0.09669043947],"iteration":206,"passed_time":0.6541977368,"remaining_time":2.506177803},
{"learn":[0.09625680872],"iteration":207,"passed_time":0.6568329652,"remaining_time":2.501017829},
{"learn":[0.09590967664],"iteration":208,"passed_time":0.6604297548,"remaining_time":2.499521225},
{"learn":[0.09581927207],"iteration":209,"passed_time":0.6631812401,"remaining_time":2.494824665},
{"learn":[0.09567194213],"iteration":210,"passed_time":0.6660832526,"remaining_time":2.490709414},
{"learn":[0.09546847015],"iteration":211,"passed_time":0.669303226,"remaining_time":2.487787463},
{"learn":[0.09506386544],"iteration":212,"passed_time":0.6728956834,"remaining_time":2.486238981},
{"learn":[0.09474628518],"iteration":213,"passed_time":0.6765862661,"remaining_time":2.4850318},
{"learn":[0.09448948255],"iteration":214,"passed_time":0.6812164056,"remaining_time":2.487231993},
{"learn":[0.09416074257],"iteration":215,"passed_time":0.6851292374,"remaining_time":2.48676538},
{"learn":[0.09393975839],"iteration":216,"passed_time":0.6892331589,"remaining_time":2.486956514},
{"learn":[0.09355137821],"iteration":217,"passed_time":0.6928162326,"remaining_time":2.48523988},
{"learn":[0.09322555692],"iteration":218,"passed_time":0.6974817931,"remaining_time":2.487366577},
{"learn":[0.09302772919],"iteration":219,"passed_time":0.7012432816,"remaining_time":2.48622618},
{"learn":[0.09271542835],"iteration":220,"passed_time":0.7053620972,"remaining_time":2.486321601},
{"learn":[0.09257953714],"iteration":221,"passed_time":0.7103166862,"remaining_time":2.489308026},
{"learn":[0.09244510527],"iteration":222,"passed_time":0.7137026897,"remaining_time":2.486757802},
{"learn":[0.09205464338],"iteration":223,"passed_time":0.7173619434,"remaining_time":2.485146732},
{"learn":[0.09187855566],"iteration":224,"passed_time":0.7215439984,"remaining_time":2.485318217},
{"learn":[0.09147383292],"iteration":225,"passed_time":0.7254671364,"remaining_time":2.484564441},
{"learn":[0.09121298488],"iteration":226,"passed_time":0.72993453,"remaining_time":2.485636087},
{"learn":[0.09082215815],"iteration":227,"passed_time":0.7336526156,"remaining_time":2.484122014},
{"learn":[0.09062166925],"iteration":228,"passed_time":0.737676311,"remaining_time":2.483617624},
{"learn":[0.09014595343],"iteration":229,"passed_time":0.7415275159,"remaining_time":2.482505162},
{"learn":[0.08994156399],"iteration":230,"passed_time":0.7461940235,"remaining_time":2.484083135},
{"learn":[0.08979086467],"iteration":231,"passed_time":0.750241046,"remaining_time":2.483556566},
{"learn":[0.08960938487],"iteration":232,"passed_time":0.7541009742,"remaining_time":2.482383894},
{"learn":[0.08925680169],"iteration":233,"passed_time":0.7573983787,"remaining_time":2.47934683},
{"learn":[0.08895415831],"iteration":234,"passed_time":0.7613960536,"remaining_time":2.478587153},
{"learn":[0.08876035452],"iteration":235,"passed_time":0.7653927375,"remaining_time":2.477796828},
{"learn":[0.08859546946],"iteration":236,"passed_time":0.7687177751,"remaining_time":2.474817141},
{"learn":[0.08814711645],"iteration":237,"passed_time":0.7721462948,"remaining_time":2.472165868},
{"learn":[0.08796204729],"iteration":238,"passed_time":0.7759278205,"remaining_time":2.470632098},
{"learn":[0.08775184728],"iteration":239,"passed_time":0.779047175,"remaining_time":2.466982721},
{"learn":[0.08757188049],"iteration":240,"passed_time":0.7822576629,"remaining_time":2.463624756},
{"learn":[0.08739195661],"iteration":241,"passed_time":0.786131078,"remaining_time":2.462344451},
{"learn":[0.08707645808],"iteration":242,"passed_time":0.7893025892,"remaining_time":2.458856214},
{"learn":[0.08676410358],"iteration":243,"passed_time":0.7928478928,"remaining_time":2.456528717},
{"learn":[0.08655710663],"iteration":244,"passed_time":0.7971816317,"remaining_time":2.456620947},
{"learn":[0.08629410176],"iteration":245,"passed_time":0.8014364164,"remaining_time":2.456435195},
{"learn":[0.0861717149],"iteration":246,"passed_time":0.8060778483,"remaining_time":2.457395222},
{"learn":[0.08600165774],"iteration":247,"passed_time":0.8098317095,"remaining_time":2.455618732},
{"learn":[0.08582363316],"iteration":248,"passed_time":0.8232585699,"remaining_time":2.483000747},
{"learn":[0.08547844867],"iteration":249,"passed_time":0.825977144,"remaining_time":2.477931432},
{"learn":[0.08525679383],"iteration":250,"passed_time":0.8292526939,"remaining_time":2.474542899},
{"learn":[0.08495694575],"iteration":251,"passed_time":0.8319546218,"remaining_time":2.469452608},
{"learn":[0.08482529309],"iteration":252,"passed_time":0.8350936664,"remaining_time":2.465671813},
{"learn":[0.08447310693],"iteration":253,"passed_time":0.8382614277,"remaining_time":2.461980414},
{"learn":[0.08438728966],"iteration":254,"passed_time":0.841429548,"remaining_time":2.45829417},
{"learn":[0.08420431832],"iteration":255,"passed_time":0.8443119654,"remaining_time":2.453781649},
{"learn":[0.08394436092],"iteration":256,"passed_time":0.8474654427,"remaining_time":2.450065463},
{"learn":[0.08350631993],"iteration":257,"passed_time":0.8504048446,"remaining_time":2.445737964},
{"learn":[0.08332931476],"iteration":258,"passed_time":0.8533896167,"remaining_time":2.441550988},
{"learn":[0.08316717134],"iteration":259,"passed_time":0.856392608,"remaining_time":2.437425115},
{"learn":[0.08302840972],"iteration":260,"passed_time":0.8593522918,"remaining_time":2.433185225},
{"learn":[0.08289981525],"iteration":261,"passed_time":0.8622143816,"remaining_time":2.428680205},
{"learn":[0.08273885756],"iteration":262,"passed_time":0.8650661345,"remaining_time":2.424158711},
{"learn":[0.08250378959],"iteration":263,"passed_time":0.8681455262,"remaining_time":2.420284497},
{"learn":[0.0823468773],"iteration":264,"passed_time":0.8709908396,"remaining_time":2.415767046},
{"learn":[0.08201777784],"iteration":265,"passed_time":0.8742010765,"remaining_time":2.412269136},
{"learn":[0.08186658492],"iteration":266,"passed_time":0.87695742,"remaining_time":2.407527299},
{"learn":[0.08166833333],"iteration":267,"passed_time":0.8802558358,"remaining_time":2.404280865},
{"learn":[0.08152864352],"iteration":268,"passed_time":0.8830731755,"remaining_time":2.399726733},
{"learn":[0.08127429281],"iteration":269,"passed_time":0.8861468573,"remaining_time":2.39587854},
{"learn":[0.08111193479],"iteration":270,"passed_time":0.8889488627,"remaining_time":2.391305243},
{"learn":[0.0808432964],"iteration":271,"passed_time":0.8923244801,"remaining_time":2.388280226},
{"learn":[0.08048580937],"iteration":272,"passed_time":0.8950103228,"remaining_time":2.383415768},
{"learn":[0.08031159413],"iteration":273,"passed_time":0.8980985838,"remaining_time":2.379633474},
{"learn":[0.08018925019],"iteration":274,"passed_time":0.9014233056,"remaining_time":2.376479624},
{"learn":[0.07988002901],"iteration":275,"passed_time":0.9048355203,"remaining_time":2.373554046},
{"learn":[0.07976195044],"iteration":276,"passed_time":0.9079036594,"remaining_time":2.36972688},
{"learn":[0.07965852976],"iteration":277,"passed_time":0.9108974562,"remaining_time":2.365712099},
{"learn":[0.07952705415],"iteration":278,"passed_time":0.9139272744,"remaining_time":2.361797723},
{"learn":[0.07933019753],"iteration":279,"passed_time":0.916810457,"remaining_time":2.357512604},
{"learn":[0.07921626095],"iteration":280,"passed_time":0.9199529733,"remaining_time":2.353901024},
{"learn":[0.07893514834],"iteration":281,"passed_time":0.9228881223,"remaining_time":2.349764794},
{"learn":[0.07879646183],"iteration":282,"passed_time":0.9259348928,"remaining_time":2.345919852},
{"learn":[0.07849943051],"iteration":283,"passed_time":0.9290753753,"remaining_time":2.342316791},
{"learn":[0.07838133049],"iteration":284,"passed_time":0.9322527858,"remaining_time":2.33880962},
{"learn":[0.07822433772],"iteration":285,"passed_time":0.9349629019,"remaining_time":2.334138154},
{"learn":[0.07807974943],"iteration":286,"passed_time":0.9380001718,"remaining_time":2.33029311},
{"learn":[0.07781230749],"iteration":287,"passed_time":0.9407916606,"remaining_time":2.32584605},
{"learn":[0.07763527013],"iteration":288,"passed_time":0.944072479,"remaining_time":2.3226143},
{"learn":[0.07751731497],"iteration":289,"passed_time":0.9472186602,"remaining_time":2.319052582},
{"learn":[0.07738360742],"iteration":290,"passed_time":0.9506353469,"remaining_time":2.316152787},
{"learn":[0.07728412483],"iteration":291,"passed_time":0.9536740994,"remaining_time":2.31233309},
{"learn":[0.07694060893],"iteration":292,"passed_time":0.956768249,"remaining_time":2.308652396},
{"learn":[0.07671156614],"iteration":293,"passed_time":0.9599780405,"remaining_time":2.30525339},
{"learn":[0.07664119543],"iteration":294,"passed_time":0.9630993181,"remaining_time":2.301644133},
{"learn":[0.07656524487],"iteration":295,"passed_time":0.9659397688,"remaining_time":2.297370261},
{"learn":[0.07650936035],"iteration":296,"passed_time":0.9689042393,"remaining_time":2.293399597},
{"learn":[0.07632384052],"iteration":297,"passed_time":0.9717298717,"remaining_time":2.289108624},
{"learn":[0.07612940363],"iteration":298,"passed_time":0.9746998665,"remaining_time":2.285165908},
{"learn":[0.07603355869],"iteration":299,"passed_time":0.9775946921,"remaining_time":2.281054282},
{"learn":[0.07583208795],"iteration":300,"passed_time":0.9807669902,"remaining_time":2.277595104},
{"learn":[0.07558598901],"iteration":301,"passed_time":0.9840172753,"remaining_time":2.274318073},
{"learn":[0.07528159655],"iteration":302,"passed_time":0.9870382893,"remaining_time":2.270513821},
{"learn":[0.0751942931],"iteration":303,"passed_time":0.9902578568,"remaining_time":2.267169304},
{"learn":[0.07503821779],"iteration":304,"passed_time":0.9931353958,"remaining_time":2.26304623},
{"learn":[0.07494478722],"iteration":305,"passed_time":0.9965753736,"remaining_time":2.260206893},
{"learn":[0.07477367846],"iteration":306,"passed_time":1.000172689,"remaining_time":2.257718807},
{"learn":[0.07455172854],"iteration":307,"passed_time":1.003435599,"remaining_time":2.254472189},
{"learn":[0.07445367848],"iteration":308,"passed_time":1.006806098,"remaining_time":2.251466063},
{"learn":[0.07428987184],"iteration":309,"passed_time":1.011028757,"remaining_time":2.250354331},
{"learn":[0.07421330963],"iteration":310,"passed_time":1.014710776,"remaining_time":2.248024838},
{"learn":[0.07416857412],"iteration":311,"passed_time":1.017727804,"remaining_time":2.244220287},
{"learn":[0.07394012151],"iteration":312,"passed_time":1.021922855,"remaining_time":2.243006395},
{"learn":[0.07352928773],"iteration":313,"passed_time":1.025912186,"remaining_time":2.241324076},
{"learn":[0.07337674813],"iteration":314,"passed_time":1.029055799,"remaining_time":2.237788008},
{"learn":[0.07325216151],"iteration":315,"passed_time":1.032976949,"remaining_time":2.235937447},
{"learn":[0.07311294384],"iteration":316,"passed_time":1.036744097,"remaining_time":2.233742014},
{"learn":[0.07301885334],"iteration":317,"passed_time":1.040281297,"remaining_time":2.231043537},
{"learn":[0.07281928726],"iteration":318,"passed_time":1.044434593,"remaining_time":2.229655041},
{"learn":[0.07254316971],"iteration":319,"passed_time":1.048227391,"remaining_time":2.227483206},
{"learn":[0.07233278728],"iteration":320,"passed_time":1.051795621,"remaining_time":2.224826251},
{"learn":[0.07218325758],"iteration":321,"passed_time":1.056104626,"remaining_time":2.223723405},
{"learn":[0.07195850163],"iteration":322,"passed_time":1.05969166,"remaining_time":2.221087474},
{"learn":[0.07182625879],"iteration":323,"passed_time":1.063112979,"remaining_time":2.21809992},
{"learn":[0.0716452726],"iteration":324,"passed_time":1.067080892,"remaining_time":2.216244929},
{"learn":[0.07145426947],"iteration":325,"passed_time":1.071088984,"remaining_time":2.214460047},
{"learn":[0.07138410265],"iteration":326,"passed_time":1.07460428,"remaining_time":2.211647341},
{"learn":[0.07117793731],"iteration":327,"passed_time":1.07821041,"remaining_time":2.20901645},
{"learn":[0.07105846915],"iteration":328,"passed_time":1.082383581,"remaining_time":2.207536118},
{"learn":[0.07095379836],"iteration":329,"passed_time":1.086041141,"remaining_time":2.20499262},
{"learn":[0.07084570454],"iteration":330,"passed_time":1.089534339,"remaining_time":2.20211019},
{"learn":[0.07075139407],"iteration":331,"passed_time":1.093467007,"remaining_time":2.200108315},
{"learn":[0.07033453511],"iteration":332,"passed_time":1.096890679,"remaining_time":2.197075325},
{"learn":[0.07017438221],"iteration":333,"passed_time":1.100574771,"remaining_time":2.194559274},
{"learn":[0.07007994296],"iteration":334,"passed_time":1.10448581,"remaining_time":2.192486757},
{"learn":[0.06984185435],"iteration":335,"passed_time":1.107775868,"remaining_time":2.189176121},
{"learn":[0.0695377999],"iteration":336,"passed_time":1.111220449,"remaining_time":2.186169608},
{"learn":[0.06942172258],"iteration":337,"passed_time":1.114906709,"remaining_time":2.183633851},
{"learn":[0.06911161613],"iteration":338,"passed_time":1.11870167,"remaining_time":2.181303256},
{"learn":[0.06903847696],"iteration":339,"passed_time":1.122023924,"remaining_time":2.17804644},
{"learn":[0.06890114786],"iteration":340,"passed_time":1.12606067,"remaining_time":2.176170034},
{"learn":[0.06878569827],"iteration":341,"passed_time":1.129807737,"remaining_time":2.173723658},
{"learn":[0.06873096729],"iteration":342,"passed_time":1.132799956,"remaining_time":2.169823823},
{"learn":[0.06862127462],"iteration":343,"passed_time":1.136666255,"remaining_time":2.167596114},
{"learn":[0.06848806604],"iteration":344,"passed_time":1.140281699,"remaining_time":2.164882646},
{"learn":[0.06833880461],"iteration":345,"passed_time":1.143664467,"remaining_time":2.161724166},
{"learn":[0.0682527137],"iteration":346,"passed_time":1.147573402,"remaining_time":2.159554558},
{"learn":[0.06819615317],"iteration":347,"passed_time":1.150960759,"remaining_time":2.156397743},
{"learn":[0.0680091096],"iteration":348,"passed_time":1.155152899,"remaining_time":2.154740795},
{"learn":[0.0678972923],"iteration":349,"passed_time":1.158893576,"remaining_time":2.152230927},
{"learn":[0.06784370948],"iteration":350,"passed_time":1.162955707,"remaining_time":2.150308415},
{"learn":[0.06767262755],"iteration":351,"passed_time":1.166228552,"remaining_time":2.146920744},
{"learn":[0.06752289934],"iteration":352,"passed_time":1.170307526,"remaining_time":2.145011244},
{"learn":[0.06718012385],"iteration":353,"passed_time":1.174919847,"remaining_time":2.144062772},
{"learn":[0.06700818884],"iteration":354,"passed_time":1.179503814,"remaining_time":2.14304214},
{"learn":[0.06683253035],"iteration":355,"passed_time":1.18299337,"remaining_time":2.140021714},
{"learn":[0.06676401602],"iteration":356,"passed_time":1.186718847,"remaining_time":2.137423582},
{"learn":[0.06651459062],"iteration":357,"passed_time":1.190694989,"remaining_time":2.135268667},
{"learn":[0.06636193298],"iteration":358,"passed_time":1.194509075,"remaining_time":2.132814254},
{"learn":[0.06627710828],"iteration":359,"passed_time":1.198715388,"remaining_time":2.131049579},
{"learn":[0.0660272161],"iteration":360,"passed_time":1.203307779,"remaining_time":2.129954766},
{"learn":[0.06593124776],"iteration":361,"passed_time":1.207342362,"remaining_time":2.127857533},
{"learn":[0.06580753031],"iteration":362,"passed_time":1.210866102,"remaining_time":2.124853187},
{"learn":[0.06575718275],"iteration":363,"passed_time":1.214110823,"remaining_time":2.12135847},
{"learn":[0.06556033686],"iteration":364,"passed_time":1.21802071,"remaining_time":2.119022332},
{"learn":[0.06544168421],"iteration":365,"passed_time":1.221619398,"remaining_time":2.11613852},
{"learn":[0.06533239394],"iteration":366,"passed_time":1.224548923,"remaining_time":2.112096644},
{"learn":[0.06525428117],"iteration":367,"passed_time":1.227995252,"remaining_time":2.108948367},
{"learn":[0.06497058251],"iteration":368,"passed_time":1.230979674,"remaining_time":2.105008603},
{"learn":[0.06492797165],"iteration":369,"passed_time":1.23412567,"remaining_time":2.101349114},
{"learn":[0.06487236613],"iteration":370,"passed_time":1.23757929,"remaining_time":2.098213945},
{"learn":[0.06468590201],"iteration":371,"passed_time":1.241041369,"remaining_time":2.095091343},
{"learn":[0.06458682719],"iteration":372,"passed_time":1.244036291,"remaining_time":2.091181648},
{"learn":[0.06452065212],"iteration":373,"passed_time":1.246962502,"remaining_time":2.087161835},
{"learn":[0.06424668603],"iteration":374,"passed_time":1.250137224,"remaining_time":2.083562039},
{"learn":[0.06413628515],"iteration":375,"passed_time":1.252956186,"remaining_time":2.079374096},
{"learn":[0.0640052334],"iteration":376,"passed_time":1.256325423,"remaining_time":2.076102755},
{"learn":[0.06391246812],"iteration":377,"passed_time":1.259164126,"remaining_time":2.071957901},
{"learn":[0.06381519602],"iteration":378,"passed_time":1.262701467,"remaining_time":2.068964673},
{"learn":[0.06363119992],"iteration":379,"passed_time":1.265530075,"remaining_time":2.064812227},
{"learn":[0.06353732939],"iteration":380,"passed_time":1.268622251,"remaining_time":2.061094944},
{"learn":[0.06337179514],"iteration":381,"passed_time":1.271306472,"remaining_time":2.056720941},
{"learn":[0.06321784984],"iteration":382,"passed_time":1.27477189,"remaining_time":2.053614246},
{"learn":[0.0630828278],"iteration":383,"passed_time":1.277519544,"remaining_time":2.049354269},
{"learn":[0.06297042568],"iteration":384,"passed_time":1.280762673,"remaining_time":2.045893621},
{"learn":[0.06290710492],"iteration":385,"passed_time":1.28350191,"remaining_time":2.041632572},
{"learn":[0.06282599298],"iteration":386,"passed_time":1.286487249,"remaining_time":2.037769208},
{"learn":[0.06272376875],"iteration":387,"passed_time":1.289330654,"remaining_time":2.033686495},
{"learn":[0.06254773469],"iteration":388,"passed_time":1.292491263,"remaining_time":2.030108385},
{"learn":[0.06245201851],"iteration":389,"passed_time":1.295353844,"remaining_time":2.026066268},
{"learn":[0.06238851534],"iteration":390,"passed_time":1.29885609,"remaining_time":2.023026492},
{"learn":[0.06230729609],"iteration":391,"passed_time":1.301829144,"remaining_time":2.01916357},
{"learn":[0.0622316889],"iteration":392,"passed_time":1.304890437,"remaining_time":2.015441464},
{"learn":[0.06207312947],"iteration":393,"passed_time":1.308393104,"remaining_time":2.012401576},
{"learn":[0.06196709055],"iteration":394,"passed_time":1.311349191,"remaining_time":2.008522179},
{"learn":[0.06175913858],"iteration":395,"passed_time":1.314448784,"remaining_time":2.004866328},
{"learn":[0.06168239932],"iteration":396,"passed_time":1.317490432,"remaining_time":2.001125266},
{"learn":[0.06150759926],"iteration":397,"passed_time":1.320969406,"remaining_time":1.998049203},
{"learn":[0.06135770473],"iteration":398,"passed_time":1.323552698,"remaining_time":1.993621984},
{"learn":[0.06122774749],"iteration":399,"passed_time":1.326716412,"remaining_time":1.990074617},
{"learn":[0.06109385215],"iteration":400,"passed_time":1.32935495,"remaining_time":1.985744676},
{"learn":[0.06089715649],"iteration":401,"passed_time":1.332690134,"remaining_time":1.982459453},
{"learn":[0.06063848675],"iteration":402,"passed_time":1.336265585,"remaining_time":1.979529911},
{"learn":[0.06042869986],"iteration":403,"passed_time":1.339262031,"remaining_time":1.975742997},
{"learn":[0.06026467325],"iteration":404,"passed_time":1.342316653,"remaining_time":1.972045453},
{"learn":[0.06005011664],"iteration":405,"passed_time":1.345376925,"remaining_time":1.968359343},
{"learn":[0.05999959203],"iteration":406,"passed_time":1.348683013,"remaining_time":1.965034463},
{"learn":[0.05990097861],"iteration":407,"passed_time":1.351477186,"remaining_time":1.960966897},
{"learn":[0.05975652445],"iteration":408,"passed_time":1.354662043,"remaining_time":1.957470092},
{"learn":[0.05957997533],"iteration":409,"passed_time":1.357488697,"remaining_time":1.953459344},
{"learn":[0.05953279326],"iteration":410,"passed_time":1.360865286,"remaining_time":1.950242466},
{"learn":[0.05943187816],"iteration":411,"passed_time":1.363838821,"remaining_time":1.946449579},
{"learn":[0.05932090856],"iteration":412,"passed_time":1.366333513,"remaining_time":1.941980078},
{"learn":[0.05927947268],"iteration":413,"passed_time":1.369625508,"remaining_time":1.938648666},
{"learn":[0.05916014938],"iteration":414,"passed_time":1.372799359,"remaining_time":1.935150904},
{"learn":[0.05908486411],"iteration":415,"passed_time":1.375535119,"remaining_time":1.931039687},
{"learn":[0.05900732006],"iteration":416,"passed_time":1.37932613,"remaining_time":1.928410393},
{"learn":[0.05896636705],"iteration":417,"passed_time":1.382235684,"remaining_time":1.92454825},
{"learn":[0.05886527489],"iteration":418,"passed_time":1.385522822,"remaining_time":1.921214224},
{"learn":[0.0587230795],"iteration":419,"passed_time":1.388313851,"remaining_time":1.917195317},
{"learn":[0.0586529717],"iteration":420,"passed_time":1.391395986,"remaining_time":1.913582603},
{"learn":[0.05854877842],"iteration":421,"passed_time":1.394713267,"remaining_time":1.910294475},
{"learn":[0.05842544727],"iteration":422,"passed_time":1.39781888,"remaining_time":1.906717479},
{"learn":[0.05826404427],"iteration":423,"passed_time":1.401355004,"remaining_time":1.903727552},
{"learn":[0.05812903296],"iteration":424,"passed_time":1.404214259,"remaining_time":1.899819291},
{"learn":[0.05797793124],"iteration":425,"passed_time":1.407517512,"remaining_time":1.896514207},
{"learn":[0.05787695712],"iteration":426,"passed_time":1.410153797,"remaining_time":1.892314112},
{"learn":[0.05782375523],"iteration":427,"passed_time":1.413589479,"remaining_time":1.889189677},
{"learn":[0.05774471964],"iteration":428,"passed_time":1.416212873,"remaining_time":1.884982636},
{"learn":[0.05767991808],"iteration":429,"passed_time":1.419470054,"remaining_time":1.881623095},
{"learn":[0.05762397991],"iteration":430,"passed_time":1.422436268,"remaining_time":1.877879899},
{"learn":[0.05754935456],"iteration":431,"passed_time":1.42665532,"remaining_time":1.875787551},
{"learn":[0.05728439138],"iteration":432,"passed_time":1.430011868,"remaining_time":1.872555957},
{"learn":[0.05711212373],"iteration":433,"passed_time":1.432772618,"remaining_time":1.868546778},
{"learn":[0.057026006],"iteration":434,"passed_time":1.436033175,"remaining_time":1.865192515},
{"learn":[0.05686880399],"iteration":435,"passed_time":1.438856945,"remaining_time":1.861273663},
{"learn":[0.05679095948],"iteration":436,"passed_time":1.442189064,"remaining_time":1.858014743},
{"learn":[0.05663576408],"iteration":437,"passed_time":1.444786277,"remaining_time":1.853812529},
{"learn":[0.05654205451],"iteration":438,"passed_time":1.44807981,"remaining_time":1.850507456},
{"learn":[0.05651066776],"iteration":439,"passed_time":1.45073259,"remaining_time":1.846386933},
{"learn":[0.05643207749],"iteration":440,"passed_time":1.454277388,"remaining_time":1.843403764},
{"learn":[0.05628795597],"iteration":441,"passed_time":1.456973307,"remaining_time":1.839346392},
{"learn":[0.05620650065],"iteration":442,"passed_time":1.460032526,"remaining_time":1.835751958},
{"learn":[0.05609283233],"iteration":443,"passed_time":1.462681782,"remaining_time":1.831646555},
{"learn":[0.05601770801],"iteration":444,"passed_time":1.465815127,"remaining_time":1.828151451},
{"learn":[0.05590369631],"iteration":445,"passed_time":1.468590491,"remaining_time":1.824213301},
{"learn":[0.05577008533],"iteration":446,"passed_time":1.471904682,"remaining_time":1.820946955},
{"learn":[0.05568433244],"iteration":447,"passed_time":1.474722511,"remaining_time":1.817068808},
{"learn":[0.05562702077],"iteration":448,"passed_time":1.477955124,"remaining_time":1.813704395},
{"learn":[0.05552848247],"iteration":449,"passed_time":1.480671114,"remaining_time":1.80970914},
{"learn":[0.05537739685],"iteration":450,"passed_time":1.483979241,"remaining_time":1.806440361},
{"learn":[0.05532743022],"iteration":451,"passed_time":1.487019475,"remaining_time":1.80284662},
{"learn":[0.05530043225],"iteration":452,"passed_time":1.490147007,"remaining_time":1.799360735},
{"learn":[0.05521878378],"iteration":453,"passed_time":1.493249175,"remaining_time":1.795845924},
{"learn":[0.05514091781],"iteration":454,"passed_time":1.496145869,"remaining_time":1.79208681},
{"learn":[0.05507547778],"iteration":455,"passed_time":1.499439562,"remaining_time":1.788805091},
{"learn":[0.05499358787],"iteration":456,"passed_time":1.502548766,"remaining_time":1.785304113},
{"learn":[0.05489679865],"iteration":457,"passed_time":1.50597999,"remaining_time":1.782185927},
{"learn":[0.05487303056],"iteration":458,"passed_time":1.508691829,"remaining_time":1.778218473},
{"learn":[0.05477048979],"iteration":459,"passed_time":1.512004767,"remaining_time":1.774962118},
{"learn":[0.05466313101],"iteration":460,"passed_time":1.514819442,"remaining_time":1.771122949},
{"learn":[0.05443405066],"iteration":461,"passed_time":1.518153539,"remaining_time":1.767893083},
{"learn":[0.05433023831],"iteration":462,"passed_time":1.521015864,"remaining_time":1.764115592},
{"learn":[0.05416747789],"iteration":463,"passed_time":1.524036683,"remaining_time":1.760525134},
{"learn":[0.05404132462],"iteration":464,"passed_time":1.526749419,"remaining_time":1.756582664},
{"learn":[0.05394759896],"iteration":465,"passed_time":1.53033787,"remaining_time":1.753648976},
{"learn":[0.05385722121],"iteration":466,"passed_time":1.53366399,"remaining_time":1.750413076},
{"learn":[0.05372568122],"iteration":467,"passed_time":1.537009495,"remaining_time":1.747198828},
{"learn":[0.05367727588],"iteration":468,"passed_time":1.541138437,"remaining_time":1.744871023},
{"learn":[0.05356348952],"iteration":469,"passed_time":1.544362951,"remaining_time":1.741515668},
{"learn":[0.05342687937],"iteration":470,"passed_time":1.548297177,"remaining_time":1.738957975},
{"learn":[0.05331235797],"iteration":471,"passed_time":1.551772961,"remaining_time":1.735881617},
{"learn":[0.05319877013],"iteration":472,"passed_time":1.554912327,"remaining_time":1.732428744},
{"learn":[0.05306281453],"iteration":473,"passed_time":1.5585339,"remaining_time":1.729512303},
{"learn":[0.05292137028],"iteration":474,"passed_time":1.561544684,"remaining_time":1.725917809},
{"learn":[0.05286672514],"iteration":475,"passed_time":1.564835683,"remaining_time":1.72263424},
{"learn":[0.05282527317],"iteration":476,"passed_time":1.568196071,"remaining_time":1.71942672},
{"learn":[0.05271316078],"iteration":477,"passed_time":1.571374638,"remaining_time":1.716020003},
{"learn":[0.05266324243],"iteration":478,"passed_time":1.574876874,"remaining_time":1.712966287},
{"learn":[0.05252195914],"iteration":479,"passed_time":1.577914611,"remaining_time":1.709407495},
{"learn":[0.05246878945],"iteration":480,"passed_time":1.581562136,"remaining_time":1.706508832},
{"learn":[0.05239167462],"iteration":481,"passed_time":1.584506174,"remaining_time":1.702851033},
{"learn":[0.05230421021],"iteration":482,"passed_time":1.588856574,"remaining_time":1.70070155},
{"learn":[0.05221841976],"iteration":483,"passed_time":1.594135492,"remaining_time":1.69953288},
{"learn":[0.05213423352],"iteration":484,"passed_time":1.598398755,"remaining_time":1.697268781},
{"learn":[0.05200397046],"iteration":485,"passed_time":1.60161984,"remaining_time":1.693894234},
{"learn":[0.05192567528],"iteration":486,"passed_time":1.60508693,"remaining_time":1.690779456},
{"learn":[0.05189904751],"iteration":487,"passed_time":1.607910405,"remaining_time":1.686987966},
{"learn":[0.05179159215],"iteration":488,"passed_time":1.611565256,"remaining_time":1.684069215},
{"learn":[0.05174806919],"iteration":489,"passed_time":1.614954003,"remaining_time":1.680870493},
{"learn":[0.05162509752],"iteration":490,"passed_time":1.61842425,"remaining_time":1.677755485},
{"learn":[0.05159513793],"iteration":491,"passed_time":1.622490763,"remaining_time":1.675254691},
{"learn":[0.05152798638],"iteration":492,"passed_time":1.625839247,"remaining_time":1.672009125},
{"learn":[0.05140480009],"iteration":493,"passed_time":1.629791541,"remaining_time":1.669381619},
{"learn":[0.0513113266],"iteration":494,"passed_time":1.633604246,"remaining_time":1.666606352},
{"learn":[0.05116648077],"iteration":495,"passed_time":1.637189763,"remaining_time":1.663596049},
{"learn":[0.05113678408],"iteration":496,"passed_time":1.640950185,"remaining_time":1.660760449},
{"learn":[0.05103857843],"iteration":497,"passed_time":1.644409524,"remaining_time":1.657617632},
{"learn":[0.05089896909],"iteration":498,"passed_time":1.64772103,"remaining_time":1.654325122},
{"learn":[0.05070646906],"iteration":499,"passed_time":1.651269148,"remaining_time":1.651269148},
{"learn":[0.05067009262],"iteration":500,"passed_time":1.654775656,"remaining_time":1.648169765},
{"learn":[0.0506301],"iteration":501,"passed_time":1.657974415,"remaining_time":1.644763464},
{"learn":[0.0505327206],"iteration":502,"passed_time":1.661439383,"remaining_time":1.64162102},
{"learn":[0.05040897632],"iteration":503,"passed_time":1.665045508,"remaining_time":1.638616214},
{"learn":[0.05039192554],"iteration":504,"passed_time":1.668287395,"remaining_time":1.635252001},
{"learn":[0.05030890893],"iteration":505,"passed_time":1.671024729,"remaining_time":1.631395684},
{"learn":[0.05020766117],"iteration":506,"passed_time":1.674753611,"remaining_time":1.628507949},
{"learn":[0.05003846245],"iteration":507,"passed_time":1.678300827,"remaining_time":1.625440959},
{"learn":[0.04998097373],"iteration":508,"passed_time":1.681808803,"remaining_time":1.622334228},
{"learn":[0.0497829904],"iteration":509,"passed_time":1.685490005,"remaining_time":1.619392358},
{"learn":[0.04974029369],"iteration":510,"passed_time":1.688213703,"remaining_time":1.615531313},
{"learn":[0.0496400868],"iteration":511,"passed_time":1.691554615,"remaining_time":1.612262992},
{"learn":[0.04954918326],"iteration":512,"passed_time":1.694491112,"remaining_time":1.608610471},
{"learn":[0.0494627919],"iteration":513,"passed_time":1.697759651,"remaining_time":1.605274689},
{"learn":[0.04934659118],"iteration":514,"passed_time":1.700997191,"remaining_time":1.601909976},
{"learn":[0.04929738105],"iteration":515,"passed_time":1.704026213,"remaining_time":1.598350169},
{"learn":[0.04923700046],"iteration":516,"passed_time":1.707200954,"remaining_time":1.594928551},
{"learn":[0.04909415587],"iteration":517,"passed_time":1.709998463,"remaining_time":1.591156871},
{"learn":[0.04894386968],"iteration":518,"passed_time":1.71329794,"remaining_time":1.58785416},
{"learn":[0.04880768337],"iteration":519,"passed_time":1.715986748,"remaining_time":1.583987767},
{"learn":[0.04870058213],"iteration":520,"passed_time":1.719198777,"remaining_time":1.580606937},
{"learn":[0.0486737934],"iteration":521,"passed_time":1.722084154,"remaining_time":1.576927635},
{"learn":[0.0485819885],"iteration":522,"passed_time":1.725498983,"remaining_time":1.573734254},
{"learn":[0.04846538538],"iteration":523,"passed_time":1.728349279,"remaining_time":1.570027208},
{"learn":[0.04844445552],"iteration":524,"passed_time":1.731725888,"remaining_time":1.566799613},
{"learn":[0.04837315663],"iteration":525,"passed_time":1.734576615,"remaining_time":1.563097558},
{"learn":[0.04832578678],"iteration":526,"passed_time":1.73840588,"remaining_time":1.560277004},
{"learn":[0.04822393812],"iteration":527,"passed_time":1.742178697,"remaining_time":1.557402168},
{"learn":[0.04808087356],"iteration":528,"passed_time":1.745487374,"remaining_time":1.554110686},
{"learn":[0.04798970712],"iteration":529,"passed_time":1.749890581,"remaining_time":1.551789761},
{"learn":[0.04793289979],"iteration":530,"passed_time":1.753980181,"remaining_time":1.549184002},
{"learn":[0.04782990833],"iteration":531,"passed_time":1.757363676,"remaining_time":1.545951504},
{"learn":[0.04777223718],"iteration":532,"passed_time":1.761306675,"remaining_time":1.543208662},
{"learn":[0.04767770137],"iteration":533,"passed_time":1.764600233,"remaining_time":1.539894585},
{"learn":[0.04764575663],"iteration":534,"passed_time":1.768405741,"remaining_time":1.537025551},
{"learn":[0.04763278881],"iteration":535,"passed_time":1.77238707,"remaining_time":1.534305225},
{"learn":[0.04753197564],"iteration":536,"passed_time":1.775625842,"remaining_time":1.530939972},
{"learn":[0.04750717743],"iteration":537,"passed_time":1.779726114,"remaining_time":1.52831499},
{"learn":[0.04747426694],"iteration":538,"passed_time":1.783724866,"remaining_time":1.525597705},
{"learn":[0.04733531217],"iteration":539,"passed_time":1.787097348,"remaining_time":1.522342185},
{"learn":[0.04722766367],"iteration":540,"passed_time":1.790898794,"remaining_time":1.519450178},
{"learn":[0.04718502597],"iteration":541,"passed_time":1.79486503,"remaining_time":1.516694066},
{"learn":[0.04713151291],"iteration":542,"passed_time":1.798257794,"remaining_time":1.513450851},
{"learn":[0.04700540256],"iteration":543,"passed_time":1.801847167,"remaining_time":1.51037189},
{"learn":[0.04698973064],"iteration":544,"passed_time":1.804563619,"remaining_time":1.506562287},
{"learn":[0.0468833698],"iteration":545,"passed_time":1.807595665,"remaining_time":1.503019106},
{"learn":[0.04676066639],"iteration":546,"passed_time":1.810293497,"remaining_time":1.499201013},
{"learn":[0.04667886232],"iteration":547,"passed_time":1.813567555,"remaining_time":1.49586229},
{"learn":[0.04646866768],"iteration":548,"passed_time":1.816272798,"remaining_time":1.492056524},
{"learn":[0.0464484031],"iteration":549,"passed_time":1.819481332,"remaining_time":1.488666544},
{"learn":[0.04639344678],"iteration":550,"passed_time":1.822342891,"remaining_time":1.484994479},
{"learn":[0.04637103611],"iteration":551,"passed_time":1.825497131,"remaining_time":1.481562889},
{"learn":[0.04633881238],"iteration":552,"passed_time":1.828519703,"remaining_time":1.478025872},
{"learn":[0.04630280614],"iteration":553,"passed_time":1.831428135,"remaining_time":1.474398823},
{"learn":[0.04619382169],"iteration":554,"passed_time":1.834635744,"remaining_time":1.471014245},
{"learn":[0.04611575184],"iteration":555,"passed_time":1.837370944,"remaining_time":1.467253056},
{"learn":[0.04592774253],"iteration":556,"passed_time":1.840852322,"remaining_time":1.46408901},
{"learn":[0.0458342905],"iteration":557,"passed_time":1.843533157,"remaining_time":1.460289705},
{"learn":[0.0457793449],"iteration":558,"passed_time":1.846735682,"remaining_time":1.456905967},
{"learn":[0.04570181159],"iteration":559,"passed_time":1.849427945,"remaining_time":1.453121957},
{"learn":[0.04554787165],"iteration":560,"passed_time":1.852649219,"remaining_time":1.449755806},
{"learn":[0.04549062436],"iteration":561,"passed_time":1.855463409,"remaining_time":1.446072906},
{"learn":[0.04546649144],"iteration":562,"passed_time":1.858807606,"remaining_time":1.442804483},
{"learn":[0.04544886121],"iteration":563,"passed_time":1.861438272,"remaining_time":1.438984196},
{"learn":[0.04533953338],"iteration":564,"passed_time":1.864929295,"remaining_time":1.435830519},
{"learn":[0.04530992253],"iteration":565,"passed_time":1.867735628,"remaining_time":1.432150641},
{"learn":[0.04526767114],"iteration":566,"passed_time":1.87171219,"remaining_time":1.42936751},
{"learn":[0.04517848448],"iteration":567,"passed_time":1.875395781,"remaining_time":1.426357355},
{"learn":[0.0451002966],"iteration":568,"passed_time":1.878663198,"remaining_time":1.423029593},
{"learn":[0.04500578761],"iteration":569,"passed_time":1.882222244,"remaining_time":1.419922044},
{"learn":[0.04497583607],"iteration":570,"passed_time":1.885686901,"remaining_time":1.416741997},
{"learn":[0.04490185991],"iteration":571,"passed_time":1.889257344,"remaining_time":1.413640111},
{"learn":[0.04482339035],"iteration":572,"passed_time":1.892920073,"remaining_time":1.41060536},
{"learn":[0.04470999566],"iteration":573,"passed_time":1.896116298,"remaining_time":1.4072222},
{"learn":[0.04466986086],"iteration":574,"passed_time":1.899884392,"remaining_time":1.404262377},
{"learn":[0.04458669134],"iteration":575,"passed_time":1.904022829,"remaining_time":1.40157236},
{"learn":[0.04446152796],"iteration":576,"passed_time":1.907468907,"remaining_time":1.398369753},
{"learn":[0.0444102522],"iteration":577,"passed_time":1.911980871,"remaining_time":1.395944511},
{"learn":[0.04435558024],"iteration":578,"passed_time":1.915712187,"remaining_time":1.39294444},
{"learn":[0.04432386084],"iteration":579,"passed_time":1.919183243,"remaining_time":1.389753383},
{"learn":[0.04424825633],"iteration":580,"passed_time":1.923380102,"remaining_time":1.38708479},
{"learn":[0.04411858345],"iteration":581,"passed_time":1.926928401,"remaining_time":1.38394514},
{"learn":[0.04394778588],"iteration":582,"passed_time":1.930471962,"remaining_time":1.3808007},
{"learn":[0.04389432915],"iteration":583,"passed_time":1.934731805,"remaining_time":1.378165121},
{"learn":[0.04383761571],"iteration":584,"passed_time":1.938531654,"remaining_time":1.375197669},
{"learn":[0.0438005713],"iteration":585,"passed_time":1.942060802,"remaining_time":1.372036129},
{"learn":[0.04376259601],"iteration":586,"passed_time":1.946426922,"remaining_time":1.369462213},
{"learn":[0.04372942531],"iteration":587,"passed_time":1.949899712,"remaining_time":1.366256261},
{"learn":[0.04370344674],"iteration":588,"passed_time":1.953068759,"remaining_time":1.362837453},
{"learn":[0.0436747775],"iteration":589,"passed_time":1.956994841,"remaining_time":1.359945567},
{"learn":[0.04361723244],"iteration":590,"passed_time":1.960699426,"remaining_time":1.356896896},
{"learn":[0.04353330373],"iteration":591,"passed_time":1.964113804,"remaining_time":1.353646},
{"learn":[0.04349648198],"iteration":592,"passed_time":1.968021448,"remaining_time":1.350733101},
{"learn":[0.04341514469],"iteration":593,"passed_time":1.971550005,"remaining_time":1.347557747},
{"learn":[0.04336025276],"iteration":594,"passed_time":1.975366455,"remaining_time":1.344577167},
{"learn":[0.04327670767],"iteration":595,"passed_time":1.980216851,"remaining_time":1.342294644},
{"learn":[0.04310766185],"iteration":596,"passed_time":1.984748686,"remaining_time":1.339788476},
{"learn":[0.04306526023],"iteration":597,"passed_time":1.989169116,"remaining_time":1.337200643},
{"learn":[0.04291750375],"iteration":598,"passed_time":1.993037497,"remaining_time":1.334237122},
{"learn":[0.04287758088],"iteration":599,"passed_time":1.996965999,"remaining_time":1.331310666},
{"learn":[0.04276839523],"iteration":600,"passed_time":2.000886678,"remaining_time":1.328375681},
{"learn":[0.04269911368],"iteration":601,"passed_time":2.004473617,"remaining_time":1.325216777},
{"learn":[0.04266754451],"iteration":602,"passed_time":2.008402449,"remaining_time":1.322281546},
{"learn":[0.04264934019],"iteration":603,"passed_time":2.011580631,"remaining_time":1.318850877},
{"learn":[0.0426163546],"iteration":604,"passed_time":2.015324532,"remaining_time":1.315790397},
{"learn":[0.04252188316],"iteration":605,"passed_time":2.018352388,"remaining_time":1.312262113},
{"learn":[0.04237494489],"iteration":606,"passed_time":2.021854368,"remaining_time":1.309042449},
{"learn":[0.04234872756],"iteration":607,"passed_time":2.024858727,"remaining_time":1.305501021},
{"learn":[0.04230694026],"iteration":608,"passed_time":2.027648823,"remaining_time":1.301823793},
{"learn":[0.04228404135],"iteration":609,"passed_time":2.030554992,"remaining_time":1.298223684},
{"learn":[0.04214388476],"iteration":610,"passed_time":2.033524771,"remaining_time":1.294666344},
{"learn":[0.04197484163],"iteration":611,"passed_time":2.036698811,"remaining_time":1.291240423},
{"learn":[0.04188309574],"iteration":612,"passed_time":2.039399327,"remaining_time":1.287516378},
{"learn":[0.04181523062],"iteration":613,"passed_time":2.042376398,"remaining_time":1.283969527},
{"learn":[0.04177336552],"iteration":614,"passed_time":2.04520827,"remaining_time":1.280333633},
{"learn":[0.04165974012],"iteration":615,"passed_time":2.048262682,"remaining_time":1.276839074},
{"learn":[0.04159009105],"iteration":616,"passed_time":2.051129169,"remaining_time":1.27322929},
{"learn":[0.04156393274],"iteration":617,"passed_time":2.054440801,"remaining_time":1.269897064},
{"learn":[0.04147610886],"iteration":618,"passed_time":2.057256122,"remaining_time":1.266259422},
{"learn":[0.04136156063],"iteration":619,"passed_time":2.060667485,"remaining_time":1.262989749},
{"learn":[0.04128951061],"iteration":620,"passed_time":2.06338037,"remaining_time":1.259293334},
{"learn":[0.04113793675],"iteration":621,"passed_time":2.066959227,"remaining_time":1.256126347},
{"learn":[0.0411099784],"iteration":622,"passed_time":2.069537009,"remaining_time":1.252352251},
{"learn":[0.04106975775],"iteration":623,"passed_time":2.072700883,"remaining_time":1.248935148},
{"learn":[0.0410277934],"iteration":624,"passed_time":2.075304637,"remaining_time":1.245182782},
{"learn":[0.04097178549],"iteration":625,"passed_time":2.078403199,"remaining_time":1.241729707},
{"learn":[0.04093148168],"iteration":626,"passed_time":2.081081179,"remaining_time":1.23802756},
{"learn":[0.04080823906],"iteration":627,"passed_time":2.084499553,"remaining_time":1.234767251},
{"learn":[0.04072159286],"iteration":628,"passed_time":2.08727085,"remaining_time":1.231124778},
{"learn":[0.04069713802],"iteration":629,"passed_time":2.09015178,"remaining_time":1.227549458},
{"learn":[0.04067954266],"iteration":630,"passed_time":2.092942498,"remaining_time":1.223923584},
{"learn":[0.04063217013],"iteration":631,"passed_time":2.096268156,"remaining_time":1.220611838},
{"learn":[0.04061738616],"iteration":632,"passed_time":2.099238507,"remaining_time":1.217094047},
{"learn":[0.04057641975],"iteration":633,"passed_time":2.102651863,"remaining_time":1.213833725},
{"learn":[0.04050779812],"iteration":634,"passed_time":2.105732362,"remaining_time":1.210381594},
{"learn":[0.04048939261],"iteration":635,"passed_time":2.108953506,"remaining_time":1.207011126},
{"learn":[0.04045836265],"iteration":636,"passed_time":2.112542128,"remaining_time":1.203850537},
{"learn":[0.04042276417],"iteration":637,"passed_time":2.115259089,"remaining_time":1.200194029},
{"learn":[0.04039785865],"iteration":638,"passed_time":2.118570335,"remaining_time":1.196876199},
{"learn":[0.04027332032],"iteration":639,"passed_time":2.121200921,"remaining_time":1.193175518},
{"learn":[0.04024383556],"iteration":640,"passed_time":2.124654666,"remaining_time":1.189939197},
{"learn":[0.04012019322],"iteration":641,"passed_time":2.127326893,"remaining_time":1.186266398},
{"learn":[0.04010561314],"iteration":642,"passed_time":2.130487956,"remaining_time":1.182868119},
{"learn":[0.03998220151],"iteration":643,"passed_time":2.13314862,"remaining_time":1.179193957},
{"learn":[0.03991787745],"iteration":644,"passed_time":2.136311312,"remaining_time":1.175799249},
{"learn":[0.0398348984],"iteration":645,"passed_time":2.139297833,"remaining_time":1.17230872},
{"learn":[0.0398017894],"iteration":646,"passed_time":2.1426827,"remaining_time":1.169037084},
{"learn":[0.03978753928],"iteration":647,"passed_time":2.145483538,"remaining_time":1.165447848},
{"learn":[0.03970151276],"iteration":648,"passed_time":2.148447298,"remaining_time":1.161949155},
{"learn":[0.03966525436],"iteration":649,"passed_time":2.15123744,"remaining_time":1.158358621},
{"learn":[0.03958854461],"iteration":650,"passed_time":2.154415667,"remaining_time":1.154978599},
{"learn":[0.03954206807],"iteration":651,"passed_time":2.15717821,"remaining_time":1.151377327},
{"learn":[0.03941096267],"iteration":652,"passed_time":2.160267752,"remaining_time":1.147952389},
{"learn":[0.0392687029],"iteration":653,"passed_time":2.163493278,"remaining_time":1.144600419},
{"learn":[0.03918808992],"iteration":654,"passed_time":2.166520452,"remaining_time":1.14114436},
{"learn":[0.03916342584],"iteration":655,"passed_time":2.170091672,"remaining_time":1.137974901},
{"learn":[0.03915230098],"iteration":656,"passed_time":2.172893487,"remaining_time":1.134402536},
{"learn":[0.03899146669],"iteration":657,"passed_time":2.176385578,"remaining_time":1.131191288},
{"learn":[0.0389256645],"iteration":658,"passed_time":2.179023034,"remaining_time":1.127536957},
{"learn":[0.03878115669],"iteration":659,"passed_time":2.182481822,"remaining_time":1.124308817},
{"learn":[0.03877036984],"iteration":660,"passed_time":2.185117611,"remaining_time":1.120657897},
{"learn":[0.03863018374],"iteration":661,"passed_time":2.188233991,"remaining_time":1.117255421},
{"learn":[0.03858322433],"iteration":662,"passed_time":2.191046027,"remaining_time":1.113699112},
{"learn":[0.03857316716],"iteration":663,"passed_time":2.194393174,"remaining_time":1.110415823},
{"learn":[0.03853667],"iteration":664,"passed_time":2.197369028,"remaining_time":1.1069453},
{"learn":[0.03848751621],"iteration":665,"passed_time":2.200703024,"remaining_time":1.103655871},
{"learn":[0.03847388041],"iteration":666,"passed_time":2.204095868,"remaining_time":1.100395688},
{"learn":[0.03841224166],"iteration":667,"passed_time":2.207256829,"remaining_time":1.097019861},
{"learn":[0.03837088895],"iteration":668,"passed_time":2.210480982,"remaining_time":1.093675942},
{"learn":[0.03834843535],"iteration":669,"passed_time":2.213269606,"remaining_time":1.090117866},
{"learn":[0.03832523062],"iteration":670,"passed_time":2.216451849,"remaining_time":1.08675508},
{"learn":[0.03821070385],"iteration":671,"passed_time":2.219298896,"remaining_time":1.083229223},
{"learn":[0.0381510422],"iteration":672,"passed_time":2.222622691,"remaining_time":1.079937028},
{"learn":[0.03809059454],"iteration":673,"passed_time":2.225271215,"remaining_time":1.076318125},
{"learn":[0.03803220982],"iteration":674,"passed_time":2.22864269,"remaining_time":1.073050184},
{"learn":[0.0379975449],"iteration":675,"passed_time":2.231353803,"remaining_time":1.069465432},
{"learn":[0.03786103937],"iteration":676,"passed_time":2.234677974,"remaining_time":1.066175754},
{"learn":[0.03779942745],"iteration":677,"passed_time":2.237282228,"remaining_time":1.062544067},
{"learn":[0.03768463779],"iteration":678,"passed_time":2.240448066,"remaining_time":1.059180897},
{"learn":[0.03766551601],"iteration":679,"passed_time":2.243055795,"remaining_time":1.055555668},
{"learn":[0.03764053538],"iteration":680,"passed_time":2.2460861,"remaining_time":1.052131374},
{"learn":[0.03757369233],"iteration":681,"passed_time":2.248664153,"remaining_time":1.048497362},
{"learn":[0.03755264443],"iteration":682,"passed_time":2.251988649,"remaining_time":1.045212887},
{"learn":[0.03749765592],"iteration":683,"passed_time":2.254528242,"remaining_time":1.041565679},
{"learn":[0.03743929534],"iteration":684,"passed_time":2.258000081,"remaining_time":1.038350402},
{"learn":[0.03740208193],"iteration":685,"passed_time":2.260834347,"remaining_time":1.034842544},
{"learn":[0.03732190085],"iteration":686,"passed_time":2.263891693,"remaining_time":1.031438282},
{"learn":[0.0372096892],"iteration":687,"passed_time":2.266597257,"remaining_time":1.0278755},
{"learn":[0.03719180143],"iteration":688,"passed_time":2.269755799,"remaining_time":1.024519671},
{"learn":[0.03710494062],"iteration":689,"passed_time":2.272528112,"remaining_time":1.020990891},
{"learn":[0.03694486551],"iteration":690,"passed_time":2.275486574,"remaining_time":1.017547542},
{"learn":[0.03690757161],"iteration":691,"passed_time":2.27823225,"remaining_time":1.014010886},
{"learn":[0.03686181134],"iteration":692,"passed_time":2.281452904,"remaining_time":1.010686929},
{"learn":[0.03681317798],"iteration":693,"passed_time":2.284284536,"remaining_time":1.007191741},
{"learn":[0.03669454411],"iteration":694,"passed_time":2.287476629,"remaining_time":1.00385665},
{"learn":[0.03656674102],"iteration":695,"passed_time":2.290356903,"remaining_time":1.000385774},
{"learn":[0.03654075708],"iteration":696,"passed_time":2.293194574,"remaining_time":0.9968980717},
{"learn":[0.03644560963],"iteration":697,"passed_time":2.296018078,"remaining_time":0.9934061025},
{"learn":[0.03639969913],"iteration":698,"passed_time":2.299434194,"remaining_time":0.9901712336},
{"learn":[0.03626491316],"iteration":699,"passed_time":2.303021669,"remaining_time":0.9870092868},
{"learn":[0.0361212772],"iteration":700,"passed_time":2.306153618,"remaining_time":0.9836518285},
{"learn":[0.03610883517],"iteration":701,"passed_time":2.309535821,"remaining_time":0.9804012459},
{"learn":[0.0358990912],"iteration":702,"passed_time":2.312301128,"remaining_time":0.9768896659},
{"learn":[0.03587351503],"iteration":703,"passed_time":2.315588861,"remaining_time":0.9735998622},
{"learn":[0.03582164104],"iteration":704,"passed_time":2.318244177,"remaining_time":0.9700454357},
{"learn":[0.03569085487],"iteration":705,"passed_time":2.32140415,"remaining_time":0.9667037113},
{"learn":[0.0356820022],"iteration":706,"passed_time":2.324034646,"remaining_time":0.9631430711},
{"learn":[0.03555129919],"iteration":707,"passed_time":2.327201069,"remaining_time":0.9598060905},
{"learn":[0.0354675529],"iteration":708,"passed_time":2.329908365,"remaining_time":0.9562811485},
{"learn":[0.03543329306],"iteration":709,"passed_time":2.333414437,"remaining_time":0.95308477},
{"learn":[0.03536096136],"iteration":710,"passed_time":2.33613214,"remaining_time":0.9495670725},
{"learn":[0.03530558655],"iteration":711,"passed_time":2.339048375,"remaining_time":0.946131927},
{"learn":[0.03528348705],"iteration":712,"passed_time":2.341774346,"remaining_time":0.9426216513},
{"learn":[0.0352588954],"iteration":713,"passed_time":2.344989205,"remaining_time":0.9393094016},
{"learn":[0.03521720736],"iteration":714,"passed_time":2.347992707,"remaining_time":0.9359131771},
{"learn":[0.03514996997],"iteration":715,"passed_time":2.351173088,"remaining_time":0.932588208},
{"learn":[0.0350314595],"iteration":716,"passed_time":2.354388402,"remaining_time":0.9292774307},
{"learn":[0.03497757623],"iteration":717,"passed_time":2.357364752,"remaining_time":0.925873064},
{"learn":[0.03486598427],"iteration":718,"passed_time":2.360253344,"remaining_time":0.9224355905},
{"learn":[0.03484615964],"iteration":719,"passed_time":2.362975469,"remaining_time":0.9189349045},
{"learn":[0.03478947571],"iteration":720,"passed_time":2.365987349,"remaining_time":0.9155485025},
{"learn":[0.03476260651],"iteration":721,"passed_time":2.368845823,"remaining_time":0.9121040703},
{"learn":[0.0347428409],"iteration":722,"passed_time":2.37182705,"remaining_time":0.9087082888},
{"learn":[0.03466987878],"iteration":723,"passed_time":2.374625259,"remaining_time":0.9052438831},
{"learn":[0.03465424979],"iteration":724,"passed_time":2.377713635,"remaining_time":0.9018913787},
{"learn":[0.03462665091],"iteration":725,"passed_time":2.381642712,"remaining_time":0.8988568913},
{"learn":[0.03459008132],"iteration":726,"passed_time":2.384937592,"remaining_time":0.8955817919},
{"learn":[0.03455878042],"iteration":727,"passed_time":2.387667895,"remaining_time":0.8920956971},
{"learn":[0.0345433875],"iteration":728,"passed_time":2.391002257,"remaining_time":0.88883623},
{"learn":[0.03447860203],"iteration":729,"passed_time":2.393835847,"remaining_time":0.8853913408},
{"learn":[0.03439189948],"iteration":730,"passed_time":2.397312608,"remaining_time":0.8821848039},
{"learn":[0.03428110962],"iteration":731,"passed_time":2.400628611,"remaining_time":0.8789186719},
{"learn":[0.03423405364],"iteration":732,"passed_time":2.403765819,"remaining_time":0.8755872766},
{"learn":[0.03409751323],"iteration":733,"passed_time":2.406860835,"remaining_time":0.8722411201},
{"learn":[0.03399064269],"iteration":734,"passed_time":2.409712313,"remaining_time":0.8688078408},
{"learn":[0.03395754443],"iteration":735,"passed_time":2.412878436,"remaining_time":0.8654890042},
{"learn":[0.03386818608],"iteration":736,"passed_time":2.415591992,"remaining_time":0.8620090827},
{"learn":[0.03378533848],"iteration":737,"passed_time":2.418821981,"remaining_time":0.8587145785},
{"learn":[0.03369661323],"iteration":738,"passed_time":2.421485072,"remaining_time":0.8552200323},
{"learn":[0.03366075454],"iteration":739,"passed_time":2.425330303,"remaining_time":0.8521430795},
{"learn":[0.03357542819],"iteration":740,"passed_time":2.428660794,"remaining_time":0.8488841372},
{"learn":[0.03350283895],"iteration":741,"passed_time":2.432524499,"remaining_time":0.8458104051},
{"learn":[0.03344302707],"iteration":742,"passed_time":2.435711329,"remaining_time":0.8425004193},
{"learn":[0.03343255409],"iteration":743,"passed_time":2.438547518,"remaining_time":0.8390701137},
{"learn":[0.03335532123],"iteration":744,"passed_time":2.441903039,"remaining_time":0.8358191609},
{"learn":[0.03330555847],"iteration":745,"passed_time":2.444625053,"remaining_time":0.8323522299},
{"learn":[0.03325711021],"iteration":746,"passed_time":2.447892305,"remaining_time":0.8290719588},
{"learn":[0.03318964211],"iteration":747,"passed_time":2.45060504,"remaining_time":0.8256049066},
{"learn":[0.03317252963],"iteration":748,"passed_time":2.45437402,"remaining_time":0.8224938306},
{"learn":[0.0331439194],"iteration":749,"passed_time":2.457460793,"remaining_time":0.8191535978},
{"learn":[0.0331373255],"iteration":750,"passed_time":2.46088695,"remaining_time":0.8159265653},
{"learn":[0.03303559219],"iteration":751,"passed_time":2.464063139,"remaining_time":0.8126165671},
{"learn":[0.0329922275],"iteration":752,"passed_time":2.467466635,"remaining_time":0.8093814857},
{"learn":[0.03289492321],"iteration":753,"passed_time":2.471402989,"remaining_time":0.806319808},
{"learn":[0.032872534],"iteration":754,"passed_time":2.474533655,"remaining_time":0.8029943648},
{"learn":[0.03278793195],"iteration":755,"passed_time":2.477943396,"remaining_time":0.7997595086},
{"learn":[0.03271721788],"iteration":756,"passed_time":2.480970985,"remaining_time":0.7964015183},
{"learn":[0.03269188045],"iteration":757,"passed_time":2.484297836,"remaining_time":0.7931399424},
{"learn":[0.03266682471],"iteration":758,"passed_time":2.488070186,"remaining_time":0.7900196507},
{"learn":[0.03260723817],"iteration":759,"passed_time":2.491132266,"remaining_time":0.7866733473},
{"learn":[0.03256541063],"iteration":760,"passed_time":2.494768052,"remaining_time":0.7835079691},
{"learn":[0.03251662435],"iteration":761,"passed_time":2.498389456,"remaining_time":0.7803368642},
{"learn":[0.03243781947],"iteration":762,"passed_time":2.501749744,"remaining_time":0.7770834721},
{"learn":[0.03241967417],"iteration":763,"passed_time":2.505153996,"remaining_time":0.773843381},
{"learn":[0.03241007305],"iteration":764,"passed_time":2.508096422,"remaining_time":0.7704609924},
{"learn":[0.03239487059],"iteration":765,"passed_time":2.511727811,"remaining_time":0.767290219},
{"learn":[0.03234239302],"iteration":766,"passed_time":2.514573926,"remaining_time":0.7638796933},
{"learn":[0.03229172622],"iteration":767,"passed_time":2.518063012,"remaining_time":0.7606648681},
{"learn":[0.03226505821],"iteration":768,"passed_time":2.52093724,"remaining_time":0.7572646326},
{"learn":[0.03218977294],"iteration":769,"passed_time":2.524293417,"remaining_time":0.7540097219},
{"learn":[0.03212723551],"iteration":770,"passed_time":2.527612104,"remaining_time":0.7507434136},
{"learn":[0.03210850808],"iteration":771,"passed_time":2.530714882,"remaining_time":0.7474132036},
{"learn":[0.03199944583],"iteration":772,"passed_time":2.53405275,"remaining_time":0.7441526188},
{"learn":[0.03195284858],"iteration":773,"passed_time":2.537075884,"remaining_time":0.7407999351},
{"learn":[0.03187459095],"iteration":774,"passed_time":2.540613655,"remaining_time":0.7375975128},
{"learn":[0.03180915092],"iteration":775,"passed_time":2.543555761,"remaining_time":0.7342222816},
{"learn":[0.03168801953],"iteration":776,"passed_time":2.547345289,"remaining_time":0.7310913765},
{"learn":[0.03167851229],"iteration":777,"passed_time":2.550304551,"remaining_time":0.7277218643},
{"learn":[0.03165734099],"iteration":778,"passed_time":2.553734945,"remaining_time":0.7244870639},
{"learn":[0.03156828042],"iteration":779,"passed_time":2.557513916,"remaining_time":0.7213500788},
{"learn":[0.0315615819],"iteration":780,"passed_time":2.560591415,"remaining_time":0.7180147501},
{"learn":[0.03151732122],"iteration":781,"passed_time":2.564191715,"remaining_time":0.7148258234},
{"learn":[0.03145422848],"iteration":782,"passed_time":2.566892983,"remaining_time":0.7113866887},
{"learn":[0.03143930234],"iteration":783,"passed_time":2.570314522,"remaining_time":0.7081478784},
{"learn":[0.03137992505],"iteration":784,"passed_time":2.573608536,"remaining_time":0.7048736754},
{"learn":[0.03132277165],"iteration":785,"passed_time":2.576587053,"remaining_time":0.7015135234},
{"learn":[0.0312997091],"iteration":786,"passed_time":2.579619431,"remaining_time":0.6981689184},
{"learn":[0.03121857033],"iteration":787,"passed_time":2.58258927,"remaining_time":0.6948082808},
{"learn":[0.03116464414],"iteration":788,"passed_time":2.585636757,"remaining_time":0.6914693988},
{"learn":[0.03112226398],"iteration":789,"passed_time":2.588907653,"remaining_time":0.6881906421},
{"learn":[0.03105477978],"iteration":790,"passed_time":2.592189924,"remaining_time":0.6849149104},
{"learn":[0.03104947354],"iteration":791,"passed_time":2.595356552,"remaining_time":0.6816087916},
{"learn":[0.03099071594],"iteration":792,"passed_time":2.598965576,"remaining_time":0.6784185048},
{"learn":[0.03097846169],"iteration":793,"passed_time":2.601806423,"remaining_time":0.6750278628},
{"learn":[0.03095759621],"iteration":794,"passed_time":2.604961924,"remaining_time":0.6717197415},
{"learn":[0.03090057158],"iteration":795,"passed_time":2.607689963,"remaining_time":0.6683024528},
{"learn":[0.03087842112],"iteration":796,"passed_time":2.610651299,"remaining_time":0.6649463158},
{"learn":[0.03081936038],"iteration":797,"passed_time":2.613505717,"remaining_time":0.6615641037},
{"learn":[0.03074254869],"iteration":798,"passed_time":2.617084128,"remaining_time":0.6583653438},
{"learn":[0.03072415123],"iteration":799,"passed_time":2.620170886,"remaining_time":0.6550427214},
{"learn":[0.03065978424],"iteration":800,"passed_time":2.62302932,"remaining_time":0.6516639634},
{"learn":[0.03060482256],"iteration":801,"passed_time":2.626144968,"remaining_time":0.6483500046},
{"learn":[0.03053797146],"iteration":802,"passed_time":2.629292426,"remaining_time":0.6450443437},
{"learn":[0.03048456034],"iteration":803,"passed_time":2.632549848,"remaining_time":0.6417658833},
{"learn":[0.03037314542],"iteration":804,"passed_time":2.635296386,"remaining_time":0.6383637208},
{"learn":[0.03033197781],"iteration":805,"passed_time":2.638557694,"remaining_time":0.6350870876},
{"learn":[0.03031855394],"iteration":806,"passed_time":2.641311494,"remaining_time":0.631689118},
{"learn":[0.03031024316],"iteration":807,"passed_time":2.644744701,"remaining_time":0.6284541864},
{"learn":[0.03028777883],"iteration":808,"passed_time":2.647692005,"remaining_time":0.6251040457},
{"learn":[0.03025407966],"iteration":809,"passed_time":2.651411302,"remaining_time":0.6219359844},
{"learn":[0.03023282251],"iteration":810,"passed_time":2.654173475,"remaining_time":0.6185435101},
{"learn":[0.03017370811],"iteration":811,"passed_time":2.657443777,"remaining_time":0.615270234},
{"learn":[0.03015986039],"iteration":812,"passed_time":2.660174835,"remaining_time":0.6118729326},
{"learn":[0.03007798389],"iteration":813,"passed_time":2.663476431,"remaining_time":0.6086076365},
{"learn":[0.02997996334],"iteration":814,"passed_time":2.666352513,"remaining_time":0.6052456624},
{"learn":[0.02997209788],"iteration":815,"passed_time":2.669134797,"remaining_time":0.6018637287},
{"learn":[0.02988726513],"iteration":816,"passed_time":2.672431621,"remaining_time":0.5985985148},
{"learn":[0.02987522013],"iteration":817,"passed_time":2.675363074,"remaining_time":0.5952519309},
{"learn":[0.02979736221],"iteration":818,"passed_time":2.67836578,"remaining_time":0.5919221077},
{"learn":[0.02978894412],"iteration":819,"passed_time":2.68115812,"remaining_time":0.5885469043},
{"learn":[0.02975975713],"iteration":820,"passed_time":2.684121099,"remaining_time":0.5852103248},
{"learn":[0.02974384914],"iteration":821,"passed_time":2.687105941,"remaining_time":0.5818793888},
{"learn":[0.02965747924],"iteration":822,"passed_time":2.690255769,"remaining_time":0.5785847765},
{"learn":[0.02955723211],"iteration":823,"passed_time":2.693635196,"remaining_time":0.5753395564},
{"learn":[0.02947539854],"iteration":824,"passed_time":2.697388117,"remaining_time":0.5721732369},
{"learn":[0.02943652189],"iteration":825,"passed_time":2.700473888,"remaining_time":0.5688649595},
{"learn":[0.02942751363],"iteration":826,"passed_time":2.703724619,"remaining_time":0.565591728},
{"learn":[0.02941181757],"iteration":827,"passed_time":2.706764398,"remaining_time":0.5622747301},
{"learn":[0.02939353278],"iteration":828,"passed_time":2.709833553,"remaining_time":0.5589644604},
{"learn":[0.02935294998],"iteration":829,"passed_time":2.712753174,"remaining_time":0.5556241441},
{"learn":[0.02933747389],"iteration":830,"passed_time":2.715812884,"remaining_time":0.5523133303},
{"learn":[0.02928289851],"iteration":831,"passed_time":2.718872229,"remaining_time":0.5490030463},
{"learn":[0.02926474784],"iteration":832,"passed_time":2.721951786,"remaining_time":0.5456974169},
{"learn":[0.02922278081],"iteration":833,"passed_time":2.725276663,"remaining_time":0.5424411584},
{"learn":[0.02917427621],"iteration":834,"passed_time":2.728164303,"remaining_time":0.5390983354},
{"learn":[0.02915645551],"iteration":835,"passed_time":2.731591687,"remaining_time":0.535862484},
{"learn":[0.02911873508],"iteration":836,"passed_time":2.73434107,"remaining_time":0.532494139},
{"learn":[0.02907796718],"iteration":837,"passed_time":2.738043025,"remaining_time":0.52931142},
{"learn":[0.02898502484],"iteration":838,"passed_time":2.741357611,"remaining_time":0.5260531292},
{"learn":[0.02893486506],"iteration":839,"passed_time":2.744922415,"remaining_time":0.5228423649},
{"learn":[0.0289236785],"iteration":840,"passed_time":2.748090767,"remaining_time":0.5195558049},
{"learn":[0.02888530619],"iteration":841,"passed_time":2.751027985,"remaining_time":0.5162261539},
{"learn":[0.02877593007],"iteration":842,"passed_time":2.754444726,"remaining_time":0.5129867402},
{"learn":[0.02876671792],"iteration":843,"passed_time":2.757180367,"remaining_time":0.5096210157},
{"learn":[0.02873068218],"iteration":844,"passed_time":2.760668377,"remaining_time":0.506394791},
{"learn":[0.02865941548],"iteration":845,"passed_time":2.763499082,"remaining_time":0.5030482962},
{"learn":[0.02862438304],"iteration":846,"passed_time":2.767255708,"remaining_time":0.4998702755},
{"learn":[0.02858284791],"iteration":847,"passed_time":2.770161066,"remaining_time":0.4965383042},
{"learn":[0.02853224013],"iteration":848,"passed_time":2.773472432,"remaining_time":0.4932795491},
{"learn":[0.02848359335],"iteration":849,"passed_time":2.776634223,"remaining_time":0.4899942746},
{"learn":[0.02843637641],"iteration":850,"passed_time":2.779743561,"remaining_time":0.4867001065},
{"learn":[0.02839801751],"iteration":851,"passed_time":2.782937893,"remaining_time":0.4834211364},
{"learn":[0.02834636618],"iteration":852,"passed_time":2.785950736,"remaining_time":0.4801110881},
{"learn":[0.02829887294],"iteration":853,"passed_time":2.789678561,"remaining_time":0.4769239695},
{"learn":[0.02824839929],"iteration":854,"passed_time":2.79362199,"remaining_time":0.4737721504},
{"learn":[0.02823525709],"iteration":855,"passed_time":2.797228942,"remaining_time":0.4705618781},
{"learn":[0.0280764455],"iteration":856,"passed_time":2.800575974,"remaining_time":0.4673073095},
{"learn":[0.02805628019],"iteration":857,"passed_time":2.803628493,"remaining_time":0.4640037832},
{"learn":[0.02801174856],"iteration":858,"passed_time":2.80689618,"remaining_time":0.46073616},
{"learn":[0.02797319383],"iteration":859,"passed_time":2.809699328,"remaining_time":0.4573929139},
{"learn":[0.02795925757],"iteration":860,"passed_time":2.814593938,"remaining_time":0.4543885685},
{"learn":[0.02794651509],"iteration":861,"passed_time":2.818733041,"remaining_time":0.4512588859},
{"learn":[0.02793077879],"iteration":862,"passed_time":2.822048874,"remaining_time":0.4479961712},
{"learn":[0.02789942155],"iteration":863,"passed_time":2.825268551,"remaining_time":0.4447181979},
{"learn":[0.02774719045],"iteration":864,"passed_time":2.828205183,"remaining_time":0.4413961846},
{"learn":[0.02769056554],"iteration":865,"passed_time":2.831208379,"remaining_time":0.4380853613},
{"learn":[0.02767303724],"iteration":866,"passed_time":2.833914138,"remaining_time":0.4347296198},
{"learn":[0.02766180508],"iteration":867,"passed_time":2.837183393,"remaining_time":0.431461069},
{"learn":[0.02760745235],"iteration":868,"passed_time":2.840266521,"remaining_time":0.4281644582},
{"learn":[0.02759656624],"iteration":869,"passed_time":2.843178764,"remaining_time":0.4248428038},
{"learn":[0.02756024882],"iteration":870,"passed_time":2.846035185,"remaining_time":0.4215138219},
{"learn":[0.02751376156],"iteration":871,"passed_time":2.849010963,"remaining_time":0.4182034441},
{"learn":[0.02745160775],"iteration":872,"passed_time":2.85194077,"remaining_time":0.4148871452},
{"learn":[0.02742030148],"iteration":873,"passed_time":2.855132737,"remaining_time":0.4116095251},
{"learn":[0.02737438025],"iteration":874,"passed_time":2.858424443,"remaining_time":0.408346349},
{"learn":[0.02735686537],"iteration":875,"passed_time":2.861199506,"remaining_time":0.4050099757},
{"learn":[0.02732085109],"iteration":876,"passed_time":2.864290676,"remaining_time":0.4017192168},
{"learn":[0.02727724228],"iteration":877,"passed_time":2.866943497,"remaining_time":0.398368003},
{"learn":[0.02727085226],"iteration":878,"passed_time":2.869880364,"remaining_time":0.395057479},
{"learn":[0.0272645454],"iteration":879,"passed_time":2.872783098,"remaining_time":0.3917431497},
{"learn":[0.02718216994],"iteration":880,"passed_time":2.875802591,"remaining_time":0.3884455258},
{"learn":[0.02712851738],"iteration":881,"passed_time":2.878598871,"remaining_time":0.3851186698},
{"learn":[0.02709974887],"iteration":882,"passed_time":2.881866875,"remaining_time":0.3818555202},
{"learn":[0.02708953342],"iteration":883,"passed_time":2.884515168,"remaining_time":0.3785110402},
{"learn":[0.02702987714],"iteration":884,"passed_time":2.888164911,"remaining_time":0.3752982653},
{"learn":[0.02694211764],"iteration":885,"passed_time":2.891100536,"remaining_time":0.3719926198},
{"learn":[0.02693779861],"iteration":886,"passed_time":2.894553706,"remaining_time":0.3687537415},
{"learn":[0.02692023276],"iteration":887,"passed_time":2.897408284,"remaining_time":0.3654388826},
{"learn":[0.02689602472],"iteration":888,"passed_time":2.900569754,"remaining_time":0.3621633776},
{"learn":[0.02687331359],"iteration":889,"passed_time":2.903462041,"remaining_time":0.3588548591},
{"learn":[0.02686111836],"iteration":890,"passed_time":2.906379548,"remaining_time":0.3555503599},
{"learn":[0.02683096562],"iteration":891,"passed_time":2.909081225,"remaining_time":0.3522205968},
{"learn":[0.0267956676],"iteration":892,"passed_time":2.911956341,"remaining_time":0.3489130218},
{"learn":[0.02675498286],"iteration":893,"passed_time":2.914773294,"remaining_time":0.3455995181},
{"learn":[0.02667633894],"iteration":894,"passed_time":2.917939823,"remaining_time":0.3423281356},
{"learn":[0.02664775017],"iteration":895,"passed_time":2.920758864,"remaining_time":0.3390166539},
{"learn":[0.02652929336],"iteration":896,"passed_time":2.924339284,"remaining_time":0.335793697},
{"learn":[0.02643944677],"iteration":897,"passed_time":2.927731937,"remaining_time":0.3325486165},
{"learn":[0.02641079094],"iteration":898,"passed_time":2.930702648,"remaining_time":0.3292558036},
{"learn":[0.02637705689],"iteration":899,"passed_time":2.93396047,"remaining_time":0.3259956078},
{"learn":[0.02632995262],"iteration":900,"passed_time":2.937765543,"remaining_time":0.322795548},
{"learn":[0.02631248066],"iteration":901,"passed_time":2.941541238,"remaining_time":0.3195909549},
{"learn":[0.02619284349],"iteration":902,"passed_time":2.944993686,"remaining_time":0.3163503738},
{"learn":[0.02606126327],"iteration":903,"passed_time":2.949493571,"remaining_time":0.3132205563},
{"learn":[0.02605173189],"iteration":904,"passed_time":2.953212277,"remaining_time":0.3100057087},
{"learn":[0.02603520153],"iteration":905,"passed_time":2.956637112,"remaining_time":0.3067592588},
{"learn":[0.02595888344],"iteration":906,"passed_time":2.960526026,"remaining_time":0.3035600005},
{"learn":[0.02592216095],"iteration":907,"passed_time":2.964343327,"remaining_time":0.3003519671},
{"learn":[0.02590395663],"iteration":908,"passed_time":2.967725946,"remaining_time":0.2970990771},
{"learn":[0.02587161487],"iteration":909,"passed_time":2.971750564,"remaining_time":0.2939093964},
{"learn":[0.02582939298],"iteration":910,"passed_time":2.975569017,"remaining_time":0.2906977415},
{"learn":[0.02582547903],"iteration":911,"passed_time":2.979086978,"remaining_time":0.287455761},
{"learn":[0.02578344224],"iteration":912,"passed_time":2.983074051,"remaining_time":0.2842578778},
{"learn":[0.02576701651],"iteration":913,"passed_time":2.9868605,"remaining_time":0.2810393906},
{"learn":[0.02572172838],"iteration":914,"passed_time":2.989989809,"remaining_time":0.2777586162},
{"learn":[0.02566263277],"iteration":915,"passed_time":2.993835415,"remaining_time":0.274543859},
{"learn":[0.02565339111],"iteration":916,"passed_time":2.997712932,"remaining_time":0.2713306143},
{"learn":[0.02562530668],"iteration":917,"passed_time":3.000833778,"remaining_time":0.2680483331},
{"learn":[0.02558481509],"iteration":918,"passed_time":3.00494432,"remaining_time":0.2648536343},
{"learn":[0.02556589451],"iteration":919,"passed_time":3.008120805,"remaining_time":0.2615757222},
{"learn":[0.02555396486],"iteration":920,"passed_time":3.011565201,"remaining_time":0.2583210107},
{"learn":[0.02551260947],"iteration":921,"passed_time":3.01564879,"remaining_time":0.2551199627},
{"learn":[0.02547999139],"iteration":922,"passed_time":3.018664297,"remaining_time":0.2518278991},
{"learn":[0.02547124871],"iteration":923,"passed_time":3.022134462,"remaining_time":0.2485738302},
{"learn":[0.02540538482],"iteration":924,"passed_time":3.024894396,"remaining_time":0.2452617078},
{"learn":[0.02536373165],"iteration":925,"passed_time":3.028031393,"remaining_time":0.2419809105},
{"learn":[0.02535411711],"iteration":926,"passed_time":3.030689332,"remaining_time":0.2386626982},
{"learn":[0.02528774084],"iteration":927,"passed_time":3.03450442,"remaining_time":0.2354356878},
{"learn":[0.02525706231],"iteration":928,"passed_time":3.037613208,"remaining_time":0.2321534314},
{"learn":[0.02519447123],"iteration":929,"passed_time":3.040565355,"remaining_time":0.2288597579},
{"learn":[0.0251729646],"iteration":930,"passed_time":3.043722353,"remaining_time":0.2255820004},
{"learn":[0.02515789896],"iteration":931,"passed_time":3.046436936,"remaining_time":0.2222722228},
{"learn":[0.02509494841],"iteration":932,"passed_time":3.049787654,"remaining_time":0.2190094028},
{"learn":[0.02505172858],"iteration":933,"passed_time":3.052458182,"remaining_time":0.2156983298},
{"learn":[0.02502649846],"iteration":934,"passed_time":3.055701341,"remaining_time":0.2124284355},
{"learn":[0.0250146949],"iteration":935,"passed_time":3.058331967,"remaining_time":0.2091167157},
{"learn":[0.02495447258],"iteration":936,"passed_time":3.061534252,"remaining_time":0.2058448856},
{"learn":[0.02491862194],"iteration":937,"passed_time":3.06419182,"remaining_time":0.2025371992},
{"learn":[0.02491226947],"iteration":938,"passed_time":3.0674897,"remaining_time":0.1992724938},
{"learn":[0.02485743924],"iteration":939,"passed_time":3.070157624,"remaining_time":0.1959675079},
{"learn":[0.02478638446],"iteration":940,"passed_time":3.073400884,"remaining_time":0.1926999491},
{"learn":[0.02473391762],"iteration":941,"passed_time":3.076080166,"remaining_time":0.1893977172},
{"learn":[0.02468297451],"iteration":942,"passed_time":3.07937718,"remaining_time":0.1861341455},
{"learn":[0.02464528627],"iteration":943,"passed_time":3.082048334,"remaining_time":0.1828333758},
{"learn":[0.02460521317],"iteration":944,"passed_time":3.085282503,"remaining_time":0.1795667065},
{"learn":[0.0245961754],"iteration":945,"passed_time":3.088125669,"remaining_time":0.1762777866},
{"learn":[0.02458578558],"iteration":946,"passed_time":3.091786434,"remaining_time":0.173035566},
{"learn":[0.02454271866],"iteration":947,"passed_time":3.094872907,"remaining_time":0.1697609611},
{"learn":[0.02448369548],"iteration":948,"passed_time":3.097771409,"remaining_time":0.166476651},
{"learn":[0.02443125278],"iteration":949,"passed_time":3.100966652,"remaining_time":0.1632087712},
{"learn":[0.02436979377],"iteration":950,"passed_time":3.103910871,"remaining_time":0.1599281101},
{"learn":[0.02435403869],"iteration":951,"passed_time":3.106823991,"remaining_time":0.1566465878},
{"learn":[0.02429441728],"iteration":952,"passed_time":3.109543387,"remaining_time":0.1533562845},
{"learn":[0.02422653338],"iteration":953,"passed_time":3.11255413,"remaining_time":0.1500812264},
{"learn":[0.02422150881],"iteration":954,"passed_time":3.115523999,"remaining_time":0.1468047958},
{"learn":[0.02420609443],"iteration":955,"passed_time":3.118553282,"remaining_time":0.143531741},
{"learn":[0.02416916537],"iteration":956,"passed_time":3.121389681,"remaining_time":0.1402505291},
{"learn":[0.02412436012],"iteration":957,"passed_time":3.124618167,"remaining_time":0.1369874353},
{"learn":[0.02409389619],"iteration":958,"passed_time":3.127589509,"remaining_time":0.1337134201},
{"learn":[0.02405983755],"iteration":959,"passed_time":3.130824725,"remaining_time":0.1304510302},
{"learn":[0.02402192396],"iteration":960,"passed_time":3.133606538,"remaining_time":0.1271702966},
{"learn":[0.02400801453],"iteration":961,"passed_time":3.137328245,"remaining_time":0.1239277269},
{"learn":[0.02397382712],"iteration":962,"passed_time":3.139984396,"remaining_time":0.1206432219},
{"learn":[0.02394594657],"iteration":963,"passed_time":3.143454311,"remaining_time":0.11739041},
{"learn":[0.02392635533],"iteration":964,"passed_time":3.146182176,"remaining_time":0.1141102343},
{"learn":[0.02389291369],"iteration":965,"passed_time":3.149471927,"remaining_time":0.1108509788},
{"learn":[0.0238388641],"iteration":966,"passed_time":3.15210689,"remaining_time":0.1075693148},
{"learn":[0.0238010766],"iteration":967,"passed_time":3.15544615,"remaining_time":0.1043122694},
{"learn":[0.02378625776],"iteration":968,"passed_time":3.158356906,"remaining_time":0.1010413458},
{"learn":[0.02377981945],"iteration":969,"passed_time":3.16120214,"remaining_time":0.09776913834},
{"learn":[0.02374683922],"iteration":970,"passed_time":3.163920433,"remaining_time":0.09449401912},
{"learn":[0.02371526737],"iteration":971,"passed_time":3.166793831,"remaining_time":0.09122451365},
{"learn":[0.02366771778],"iteration":972,"passed_time":3.169522982,"remaining_time":0.08795181964},
{"learn":[0.02362266841],"iteration":973,"passed_time":3.172864164,"remaining_time":0.08469657934},
{"learn":[0.02360821173],"iteration":974,"passed_time":3.175767659,"remaining_time":0.08142993998},
{"learn":[0.02356690462],"iteration":975,"passed_time":3.178837666,"remaining_time":0.07816813933},
{"learn":[0.02355895867],"iteration":976,"passed_time":3.181574859,"remaining_time":0.07489889637},
{"learn":[0.02353606244],"iteration":977,"passed_time":3.18481322,"remaining_time":0.07164201518},
{"learn":[0.02352145553],"iteration":978,"passed_time":3.188835565,"remaining_time":0.06840198862},
{"learn":[0.02343387845],"iteration":979,"passed_time":3.19279543,"remaining_time":0.06515909042},
{"learn":[0.02341078371],"iteration":980,"passed_time":3.196792274,"remaining_time":0.06191544669},
{"learn":[0.02338736436],"iteration":981,"passed_time":3.200035943,"remaining_time":0.05865646332},
{"learn":[0.02336823722],"iteration":982,"passed_time":3.203187659,"remaining_time":0.05539592085},
{"learn":[0.0233458185],"iteration":983,"passed_time":3.206416505,"remaining_time":0.05213685374},
{"learn":[0.02332305908],"iteration":984,"passed_time":3.209080599,"remaining_time":0.0488692477},
{"learn":[0.02329714221],"iteration":985,"passed_time":3.212281386,"remaining_time":0.04561048621},
{"learn":[0.02322073023],"iteration":986,"passed_time":3.214905903,"remaining_time":0.04234425201},
{"learn":[0.02319247947],"iteration":987,"passed_time":3.218197363,"remaining_time":0.03908741736},
{"learn":[0.02313026396],"iteration":988,"passed_time":3.220890792,"remaining_time":0.03582386118},
{"learn":[0.02310202125],"iteration":989,"passed_time":3.224319142,"remaining_time":0.03256888022},
{"learn":[0.02307560273],"iteration":990,"passed_time":3.227184372,"remaining_time":0.02930843527},
{"learn":[0.02301072068],"iteration":991,"passed_time":3.230358422,"remaining_time":0.0260512776},
{"learn":[0.0230004945],"iteration":992,"passed_time":3.233053594,"remaining_time":0.02279091154},
{"learn":[0.02293735617],"iteration":993,"passed_time":3.236192048,"remaining_time":0.01953435844},
{"learn":[0.02293263206],"iteration":994,"passed_time":3.238745488,"remaining_time":0.01627510296},
{"learn":[0.02292041805],"iteration":995,"passed_time":3.241796134,"remaining_time":0.01301926158},
{"learn":[0.02285724216],"iteration":996,"passed_time":3.244461174,"remaining_time":0.009762671538},
{"learn":[0.02282533766],"iteration":997,"passed_time":3.248412091,"remaining_time":0.006509843869},
{"learn":[0.02279010671],"iteration":998,"passed_time":3.252126861,"remaining_time":0.003255382243},
{"learn":[0.0227455107],"iteration":999,"passed_time":3.263884667,"remaining_time":0}
]}